{
  "sources": [
    {
      "title": "Decrypt",
      "feedUrl": "https://decrypt.co/feed",
      "siteUrl": "https://decrypt.co/feed",
      "articles": [
        {
          "id": "https://decrypt.co/?p=226402",
          "author": "Ryan Kawailani Ozawa",
          "description": "Nearly one out of five voters own crypto, making them a potentially powerful constituency in November.",
          "link": "https://decrypt.co/226402/bitcoin-crypto-voters-biden-trump-election-2024",
          "publishedOn": "2024-04-14T17:31:01.000Z",
          "wordCount": 11066,
          "title": "Crypto Owners a Growing Force Heading into 2024 Election: Galaxy Digital",
          "enclosure": {
            "url": "https://img.decrypt.co/insecure/rs:fill:1024:512:1:0/plain/https://cdn.decrypt.co/wp-content/uploads/2024/04/Dall-E-Bitcoin-Rising-Over-White-House-gID_7.webp@png",
            "length": "1000000",
            "type": "image/png"
          },
          "imageUrl": "https://img.decrypt.co/insecure/rs:fill:1024:512:1:0/plain/https://cdn.decrypt.co/wp-content/uploads/2024/04/Dall-E-Bitcoin-Rising-Over-White-House-gID_7.webp@png"
        },
        {
          "id": "https://decrypt.co/?p=226431",
          "author": "Ryan Gladwin",
          "description": "The Sui network is getting its own gaming handheld, Saga's mainnet and token launched, and Notcoin reveals more details for its 4/20 rollout.",
          "link": "https://decrypt.co/226431/this-week-crypto-games-sui-handheld-saga-launch-notcoin-airdrop",
          "publishedOn": "2024-04-14T17:07:38.000Z",
          "wordCount": 12738,
          "title": "This Week in Crypto Games: Sui Handheld, Saga Launch, Notcoin Airdrop Nears on 4/20",
          "enclosure": {
            "url": "https://img.decrypt.co/insecure/rs:fill:1024:512:1:0/plain/https://cdn.decrypt.co/wp-content/uploads/2024/04/suiplay-blue-gID_7.png@png",
            "length": "1000000",
            "type": "image/png"
          },
          "imageUrl": "https://img.decrypt.co/insecure/rs:fill:1024:512:1:0/plain/https://cdn.decrypt.co/wp-content/uploads/2024/04/suiplay-blue-gID_7.png@png"
        },
        {
          "id": "https://decrypt.co/?p=226059",
          "author": "Stephen Graves",
          "description": "For musicians, AI is a “deeper tool” that can help stimulate creativity, said Avenged Sevenfold’s Matt Sanders (aka M. Shadows).",
          "link": "https://decrypt.co/226059/ai-human-music-fans-wont-care-avenged-sevenfold-frontman",
          "publishedOn": "2024-04-14T16:41:16.000Z",
          "wordCount": 11379,
          "title": "AI or Human? Music Fans Won’t Care, Says Avenged Sevenfold Frontman",
          "enclosure": {
            "url": "https://img.decrypt.co/insecure/rs:fill:1024:512:1:0/plain/https://cdn.decrypt.co/wp-content/uploads/2024/04/avenged-sevenfold-1-gID_7.jpg@png",
            "length": "1000000",
            "type": "image/png"
          },
          "imageUrl": "https://img.decrypt.co/insecure/rs:fill:1024:512:1:0/plain/https://cdn.decrypt.co/wp-content/uploads/2024/04/avenged-sevenfold-1-gID_7.jpg@png"
        },
        {
          "id": "https://decrypt.co/?p=226137",
          "author": "Ben Weiss",
          "description": "At the Park Hyatt in the center of Paris, Crypto.com President Eric Anziani spoke with Decrypt about regulation and his exchange’s expansions abroad.",
          "link": "https://decrypt.co/226137/crypto-sponsorships-sec-scrutiny-worth-trade-off",
          "publishedOn": "2024-04-14T14:01:02.000Z",
          "wordCount": 11359,
          "title": "Crypto.com Sponsorships May Attract SEC Scrutiny—Exec Says It’s Worth the ‘Trade Off’",
          "enclosure": {
            "url": "https://img.decrypt.co/insecure/rs:fill:1024:512:1:0/plain/https://cdn.decrypt.co/wp-content/uploads/2024/04/crypto-arena-gID_1.jpeg@png",
            "length": "1000000",
            "type": "image/png"
          },
          "imageUrl": "https://img.decrypt.co/insecure/rs:fill:1024:512:1:0/plain/https://cdn.decrypt.co/wp-content/uploads/2024/04/crypto-arena-gID_1.jpeg@png"
        },
        {
          "id": "https://decrypt.co/?p=226379",
          "author": "Sander Lutz",
          "description": "Never-ending legal drama kept crypto users on edge this week, while frothing excitement about the debut of Bitcoin-hosted meme coins offered degens a silver lining.",
          "link": "https://decrypt.co/226379/this-week-on-crypto-twitter-sec-targets-uniswap-bitcoin-runes-stir-hype",
          "publishedOn": "2024-04-14T11:01:02.000Z",
          "wordCount": 12216,
          "title": "This Week on Crypto Twitter: SEC Targets Uniswap, Bitcoin Runes Stir Hype",
          "enclosure": {
            "url": "https://img.decrypt.co/insecure/rs:fill:1024:512:1:0/plain/https://cdn.decrypt.co/wp-content/uploads/2022/07/lawsuit-scales-justice-court-gID_7.jpeg@png",
            "length": "1000000",
            "type": "image/png"
          },
          "imageUrl": "https://img.decrypt.co/insecure/rs:fill:1024:512:1:0/plain/https://cdn.decrypt.co/wp-content/uploads/2022/07/lawsuit-scales-justice-court-gID_7.jpeg@png"
        },
        {
          "id": "https://decrypt.co/?p=226366",
          "author": "Jose Antonio Lanz",
          "description": "The makers of the first AI-first wearables made a lot of promises, and reviewers say the actual gadget falls far short.",
          "link": "https://decrypt.co/226366/humane-ai-pin-review-recap",
          "publishedOn": "2024-04-13T20:00:14.000Z",
          "wordCount": 12417,
          "title": "Humane AI Pin Reviews Pile On a Half-Baked Device",
          "enclosure": {
            "url": "https://img.decrypt.co/insecure/rs:fill:1024:512:1:0/plain/https://cdn.decrypt.co/wp-content/uploads/2024/04/Humane-AI-Pin-Shutterstock-gID_7.jpg@png",
            "length": "1000000",
            "type": "image/png"
          },
          "imageUrl": "https://img.decrypt.co/insecure/rs:fill:1024:512:1:0/plain/https://cdn.decrypt.co/wp-content/uploads/2024/04/Humane-AI-Pin-Shutterstock-gID_7.jpg@png"
        },
        {
          "id": "https://decrypt.co/?p=226265",
          "author": "Jason Nelson",
          "description": "NASA says it is sticking with tried-and-true tech for its October mission to an icy moon of Jupiter.",
          "link": "https://decrypt.co/226265/nasa-europa-jupiter-clipper-mission-ai",
          "publishedOn": "2024-04-13T19:01:02.000Z",
          "wordCount": 14416,
          "title": "NASA’s Next Deep Space Mission Won’t Use Artificial Intelligence",
          "enclosure": {
            "url": "https://img.decrypt.co/insecure/rs:fill:1024:512:1:0/plain/https://cdn.decrypt.co/wp-content/uploads/2024/04/Decrypt-Wallpaper-Format-1600-x-900-px-58-gID_7.png@png",
            "length": "1000000",
            "type": "image/png"
          },
          "imageUrl": "https://img.decrypt.co/insecure/rs:fill:1024:512:1:0/plain/https://cdn.decrypt.co/wp-content/uploads/2024/04/Decrypt-Wallpaper-Format-1600-x-900-px-58-gID_7.png@png"
        },
        {
          "id": "https://decrypt.co/videos/interviews/0WGP33Rp/nasas-next-deep-space-mission-wont-use-artificial-intelligence",
          "author": null,
          "description": "On Thursday, Decrypt Media visited NASA's Jet Propulsion Laboratory in Pasadena, CA to meet with the Engineering team behind the Europa Clipper before its launch to Jupiter's Europa moon in October.",
          "link": "https://decrypt.co/videos/interviews/0WGP33Rp/nasas-next-deep-space-mission-wont-use-artificial-intelligence",
          "publishedOn": "2024-04-13T18:42:20.000Z",
          "wordCount": 6817,
          "title": "NASA’s Next Deep Space Mission Won’t Use Artificial Intelligence",
          "enclosure": {
            "url": "https://cdn.jwplayer.com/v2/media/0WGP33Rp/poster.jpg",
            "length": "1000000",
            "type": "image/png"
          },
          "imageUrl": "https://cdn.jwplayer.com/v2/media/0WGP33Rp/poster.jpg"
        },
        {
          "id": "https://decrypt.co/?p=226138",
          "author": "Jason Nelson",
          "description": "As the halving cuts miner rewards in half, there are other ways to participate in the Bitcoin network. Here are the simplest ways to connect your PC.",
          "link": "https://decrypt.co/226138/how-to-set-up-a-bitcoin-node-a-guide-for-beginners",
          "publishedOn": "2024-04-13T18:01:02.000Z",
          "wordCount": 13283,
          "title": "How to Set Up a Bitcoin Node: A Guide for Beginners",
          "enclosure": {
            "url": "https://img.decrypt.co/insecure/rs:fill:1024:512:1:0/plain/https://cdn.decrypt.co/wp-content/uploads/2021/02/Bitcoin-Network-gID_7.jpg@png",
            "length": "1000000",
            "type": "image/png"
          },
          "imageUrl": "https://img.decrypt.co/insecure/rs:fill:1024:512:1:0/plain/https://cdn.decrypt.co/wp-content/uploads/2021/02/Bitcoin-Network-gID_7.jpg@png"
        },
        {
          "id": "https://decrypt.co/?p=226119",
          "author": "Mathew Di Salvo",
          "description": "The W token took one of the biggest Ls, down over 30% over the past seven days.",
          "link": "https://decrypt.co/226119/this-week-in-coins-bitcoin-brings-down-market-week-before-halving",
          "publishedOn": "2024-04-13T17:30:42.000Z",
          "wordCount": 9994,
          "title": "This Week in Coins: Bitcoin Brings Entire Crypto Market Down One Week Before Halving",
          "enclosure": {
            "url": "https://img.decrypt.co/insecure/rs:fill:1024:512:1:0/plain/https://cdn.decrypt.co/wp-content/uploads/2019/12/shutterstock_1038671149-gID_7.jpg@png",
            "length": "1000000",
            "type": "image/png"
          },
          "imageUrl": "https://img.decrypt.co/insecure/rs:fill:1024:512:1:0/plain/https://cdn.decrypt.co/wp-content/uploads/2019/12/shutterstock_1038671149-gID_7.jpg@png"
        },
        {
          "id": "https://decrypt.co/?p=226248",
          "author": "Andrew Hayward",
          "description": "You can stack up satoshis while playing Bitcoin games on iOS and Android—and these are actually fun.",
          "link": "https://decrypt.co/226248/play-games-earn-bitcoin-best-ios-android-games-pay-btc",
          "publishedOn": "2024-04-13T13:01:02.000Z",
          "wordCount": 13231,
          "title": "Play Games, Earn Bitcoin: The Best iOS and Android Games That Pay You BTC",
          "enclosure": {
            "url": "https://img.decrypt.co/insecure/rs:fill:1024:512:1:0/plain/https://cdn.decrypt.co/wp-content/uploads/2024/04/ODPj15XCS8uPJWUEPK-AZw-gID_7.png@png",
            "length": "1000000",
            "type": "image/png"
          },
          "imageUrl": "https://img.decrypt.co/insecure/rs:fill:1024:512:1:0/plain/https://cdn.decrypt.co/wp-content/uploads/2024/04/ODPj15XCS8uPJWUEPK-AZw-gID_7.png@png"
        },
        {
          "id": "https://decrypt.co/?p=226124",
          "author": "Ryan Gladwin",
          "description": "The webcomic-based Kaidro: Clan Battles is launching on Ronin after migrating from Immutable. Here's why they moved—and what's next.",
          "link": "https://decrypt.co/226124/match-made-heaven-why-ethereum-rpg-kaidro-migrated-ronin",
          "publishedOn": "2024-04-12T20:54:04.000Z",
          "wordCount": 12683,
          "title": "'Match Made in Heaven': Why Ethereum RPG Kaidro Migrated to Ronin",
          "enclosure": {
            "url": "https://img.decrypt.co/insecure/rs:fill:1024:512:1:0/plain/https://cdn.decrypt.co/wp-content/uploads/2024/04/kaidro-mechs-gID_7.png@png",
            "length": "1000000",
            "type": "image/png"
          },
          "imageUrl": "https://img.decrypt.co/insecure/rs:fill:1024:512:1:0/plain/https://cdn.decrypt.co/wp-content/uploads/2024/04/kaidro-mechs-gID_7.png@png"
        },
        {
          "id": "https://decrypt.co/?p=225346",
          "author": "Ryan Gladwin",
          "description": "Saga is a new layer-1 blockchain with a major gaming focus, and after launching the SAGA token, there are more airdrops and rewards to come.",
          "link": "https://decrypt.co/resources/what-is-saga-gaming-network-airdrop-token-launch",
          "publishedOn": "2024-04-12T20:28:18.000Z",
          "wordCount": 13644,
          "title": "What is Saga? The Layer-1 Network, Upcoming Airdrop, and Game Publisher",
          "enclosure": {
            "url": "https://img.decrypt.co/insecure/rs:fill:1024:512:1:0/plain/https://cdn.decrypt.co/wp-content/uploads/2019/03/gaming_litepaper-gID_7-pID_5.png@png",
            "length": "1000000",
            "type": "image/png"
          },
          "imageUrl": "https://img.decrypt.co/insecure/rs:fill:1024:512:1:0/plain/https://cdn.decrypt.co/wp-content/uploads/2019/03/gaming_litepaper-gID_7-pID_5.png@png"
        },
        {
          "id": "https://decrypt.co/?p=226106",
          "author": "Ryan Gladwin",
          "description": "Founded by pseudonymous devs with bear-themed names, Berachain is built on Cosmos SDK and aims to be the next big layer-1 chain.",
          "link": "https://decrypt.co/226106/what-is-berachain-ethereum-solana-challenger-raise-big-money",
          "publishedOn": "2024-04-12T18:56:39.000Z",
          "wordCount": 11079,
          "title": "What Is Berachain? The Latest Ethereum, Solana Challenger to Raise Big Money",
          "enclosure": {
            "url": "https://img.decrypt.co/insecure/rs:fill:1024:512:1:0/plain/https://cdn.decrypt.co/wp-content/uploads/2024/04/bear-shutterstock-gID_7.png@png",
            "length": "1000000",
            "type": "image/png"
          },
          "imageUrl": "https://img.decrypt.co/insecure/rs:fill:1024:512:1:0/plain/https://cdn.decrypt.co/wp-content/uploads/2024/04/bear-shutterstock-gID_7.png@png"
        },
        {
          "id": "https://decrypt.co/?p=226104",
          "author": "Jason Nelson",
          "description": "The expected regulatory nod would open one of the world's largest financial markets to both spot Bitcoin and Ethereum exchange-traded funds.",
          "link": "https://decrypt.co/226104/ethereum-etf-hong-kong-approval-report",
          "publishedOn": "2024-04-12T18:41:02.000Z",
          "wordCount": 9923,
          "title": "Ethereum ETF Approval Could Come Monday—In Hong Kong: Report",
          "enclosure": {
            "url": "https://img.decrypt.co/insecure/rs:fill:1024:512:1:0/plain/https://cdn.decrypt.co/wp-content/uploads/2023/11/ethereum-eth-green-background-gID_7.jpg@png",
            "length": "1000000",
            "type": "image/png"
          },
          "imageUrl": "https://img.decrypt.co/insecure/rs:fill:1024:512:1:0/plain/https://cdn.decrypt.co/wp-content/uploads/2023/11/ethereum-eth-green-background-gID_7.jpg@png"
        },
        {
          "id": "https://decrypt.co/?p=226103",
          "author": "Mathew Di Salvo",
          "description": "Bitcoin, Ethereum, Solana, and other major cryptocurrencies are down significantly as traders' long positions are being liquidated.",
          "link": "https://decrypt.co/226103/bitcoin-ethereum-solana-sink-200-million-longs-liquidated",
          "publishedOn": "2024-04-12T18:24:06.000Z",
          "wordCount": 9408,
          "title": "Bitcoin, Ethereum, Solana Sink as Over $200 Million in Crypto Longs Liquidated",
          "enclosure": {
            "url": "https://img.decrypt.co/insecure/rs:fill:1024:512:1:0/plain/https://cdn.decrypt.co/wp-content/uploads/2023/04/bitcoin-crash-gID_7.jpg@png",
            "length": "1000000",
            "type": "image/png"
          },
          "imageUrl": "https://img.decrypt.co/insecure/rs:fill:1024:512:1:0/plain/https://cdn.decrypt.co/wp-content/uploads/2023/04/bitcoin-crash-gID_7.jpg@png"
        },
        {
          "id": "https://decrypt.co/?p=226071",
          "author": "Jose Antonio Lanz",
          "description": "The text-to-image generator from Google alums adds new features to close the gap with other top players—for a price.",
          "link": "https://decrypt.co/226071/ideogram-upgrade-compared-midjourney-stable-diffusion",
          "publishedOn": "2024-04-12T18:12:31.000Z",
          "wordCount": 11032,
          "title": "Ideogram AI Image Generator Upgrade Stands Strong Against Midjourney and Stable Diffusion",
          "enclosure": {
            "url": "https://img.decrypt.co/insecure/rs:fill:1024:512:1:0/plain/https://cdn.decrypt.co/wp-content/uploads/2024/04/Firefly-20240412120436-gID_7.png@png",
            "length": "1000000",
            "type": "image/png"
          },
          "imageUrl": "https://img.decrypt.co/insecure/rs:fill:1024:512:1:0/plain/https://cdn.decrypt.co/wp-content/uploads/2024/04/Firefly-20240412120436-gID_7.png@png"
        },
        {
          "id": "https://decrypt.co/?p=226096",
          "author": "Mathew Di Salvo",
          "description": "BlackRock's iShares Bitcoin Trust (IBIT) has been a massive success, netting $15 billion in inflows since its January 11 launch.",
          "link": "https://decrypt.co/226096/blackrock-bitcoin-etf-continues-rise-15-billion-total-gains",
          "publishedOn": "2024-04-12T17:46:39.000Z",
          "wordCount": 9701,
          "title": "BlackRock Bitcoin ETF Continues Rise, Crossing $15 Billion in Total Gains",
          "enclosure": {
            "url": "https://img.decrypt.co/insecure/rs:fill:1024:512:1:0/plain/https://cdn.decrypt.co/wp-content/uploads/2023/11/bitcoin-rain-gID_7.jpg@png",
            "length": "1000000",
            "type": "image/png"
          },
          "imageUrl": "https://img.decrypt.co/insecure/rs:fill:1024:512:1:0/plain/https://cdn.decrypt.co/wp-content/uploads/2023/11/bitcoin-rain-gID_7.jpg@png"
        },
        {
          "id": "https://decrypt.co/?p=226086",
          "author": "Ryan Gladwin",
          "description": "Another crypto gaming handheld is hitting the market, this time taking inspiration from the Game Boy. Here’s what you need to know.",
          "link": "https://decrypt.co/226086/bitboy-one-preview-bitcoin-gaming-handheld-price-date",
          "publishedOn": "2024-04-12T16:34:37.000Z",
          "wordCount": 11978,
          "title": "BitBoy One Preview: Everything You Need to Know About the Bitcoin Gaming Handheld",
          "enclosure": {
            "url": "https://img.decrypt.co/insecure/rs:fill:1024:512:1:0/plain/https://cdn.decrypt.co/wp-content/uploads/2024/04/bitboy-one-shadowy-gID_7.png@png",
            "length": "1000000",
            "type": "image/png"
          },
          "imageUrl": "https://img.decrypt.co/insecure/rs:fill:1024:512:1:0/plain/https://cdn.decrypt.co/wp-content/uploads/2024/04/bitboy-one-shadowy-gID_7.png@png"
        },
        {
          "id": "https://decrypt.co/?p=226084",
          "author": "Ben Weiss",
          "description": "At Paris Blockchain Week, Animoca Brands Chairman Yat Siu discussed SEC regulation, the resurgence of the NFT market, and his company’s financials.",
          "link": "https://decrypt.co/226084/nfts-lag-bitcoin-boom-animoca-yat-siu-still-believer",
          "publishedOn": "2024-04-12T16:00:12.000Z",
          "wordCount": 11024,
          "title": "NFTs Lag Behind Bitcoin's Boom—But Animoca's Yat Siu Is Still a Believer",
          "enclosure": {
            "url": "https://img.decrypt.co/insecure/rs:fill:1024:512:1:0/plain/https://cdn.decrypt.co/wp-content/uploads/2023/03/animoca-yat-siu-gID_7.jpeg@png",
            "length": "1000000",
            "type": "image/png"
          },
          "imageUrl": "https://img.decrypt.co/insecure/rs:fill:1024:512:1:0/plain/https://cdn.decrypt.co/wp-content/uploads/2023/03/animoca-yat-siu-gID_7.jpeg@png"
        },
        {
          "id": "https://decrypt.co/?p=225742",
          "author": "Decrypt Staff",
          "description": "Activity in Polkadot’s ecosystem grew apace in March, while the community voted to selected IndyCar racer Conor Daly as a brand ambassador.",
          "link": "https://decrypt.co/225742/the-week-in-polkadot-active-addresses-hit-all-time-high",
          "publishedOn": "2024-04-12T15:19:02.000Z",
          "wordCount": 10606,
          "title": "The Week in Polkadot: Active Addresses Hit All-Time High",
          "enclosure": {
            "url": "https://img.decrypt.co/insecure/rs:fill:1024:512:1:0/plain/https://cdn.decrypt.co/wp-content/uploads/2021/05/Polkadot-Kusama-Parachains-cover-gID_7.jpg@png",
            "length": "1000000",
            "type": "image/png"
          },
          "imageUrl": "https://img.decrypt.co/insecure/rs:fill:1024:512:1:0/plain/https://cdn.decrypt.co/wp-content/uploads/2021/05/Polkadot-Kusama-Parachains-cover-gID_7.jpg@png"
        },
        {
          "id": "https://decrypt.co/?p=226055",
          "author": "Stacy Elliott",
          "description": "Solana developers have pushed a congestion fix to a devnet and are urging validators to \"please upgrade ASAP\" so it can be tested.",
          "link": "https://decrypt.co/226055/solana-congestion-fix-nears-devs-upgrade-asap",
          "publishedOn": "2024-04-12T14:54:15.000Z",
          "wordCount": 10433,
          "title": "Solana Congestion Fix Nears as Devs Ask Validators to 'Upgrade ASAP'",
          "enclosure": {
            "url": "https://img.decrypt.co/insecure/rs:fill:1024:512:1:0/plain/https://cdn.decrypt.co/wp-content/uploads/2024/04/solana-tech-gID_7.png@png",
            "length": "1000000",
            "type": "image/png"
          },
          "imageUrl": "https://img.decrypt.co/insecure/rs:fill:1024:512:1:0/plain/https://cdn.decrypt.co/wp-content/uploads/2024/04/solana-tech-gID_7.png@png"
        },
        {
          "id": "https://decrypt.co/?p=226028",
          "author": "Ryan Gladwin",
          "description": "Bitcoin meme coin, PUPS, found itself in the middle of controversy with viral crypto trader Ansem colorfully coming to its defense.",
          "link": "https://decrypt.co/226028/bitcoin-pups-gains-amid-first-memecoin-controversy",
          "publishedOn": "2024-04-12T11:42:25.000Z",
          "wordCount": 10239,
          "title": "Bitcoin PUPS Up 81% Amid ‘First Meme Coin’ on BTC Network Controversy",
          "enclosure": {
            "url": "https://img.decrypt.co/insecure/rs:fill:1024:512:1:0/plain/https://cdn.decrypt.co/wp-content/uploads/2024/04/dogs-biting-angry-scared-gID_7.jpg@png",
            "length": "1000000",
            "type": "image/png"
          },
          "imageUrl": "https://img.decrypt.co/insecure/rs:fill:1024:512:1:0/plain/https://cdn.decrypt.co/wp-content/uploads/2024/04/dogs-biting-angry-scared-gID_7.jpg@png"
        },
        {
          "id": "https://decrypt.co/?p=226008",
          "author": "Stephen Graves",
          "description": "The founder of collapsed crypto exchange FTX has filed an appeal to both his federal conviction and sentencing.",
          "link": "https://decrypt.co/226008/ftx-founder-sam-bankman-fried-appeals-jail-sentence",
          "publishedOn": "2024-04-12T11:18:34.000Z",
          "wordCount": 9906,
          "title": "FTX Founder Sam Bankman-Fried Appeals 25-Year Jail Sentence",
          "enclosure": {
            "url": "https://img.decrypt.co/insecure/rs:fill:1024:512:1:0/plain/https://cdn.decrypt.co/wp-content/uploads/2022/12/sam-bankman-fried-gID_7.jpg@png",
            "length": "1000000",
            "type": "image/png"
          },
          "imageUrl": "https://img.decrypt.co/insecure/rs:fill:1024:512:1:0/plain/https://cdn.decrypt.co/wp-content/uploads/2022/12/sam-bankman-fried-gID_7.jpg@png"
        },
        {
          "id": "https://decrypt.co/?p=226007",
          "author": "Decrypt Staff",
          "description": "\"The guy who wants to tell you how to use Bitcoin couldn’t even secure his own Bitcoin,\" a developer complained on Twitter.",
          "link": "https://decrypt.co/226007/fbi-subpoena-bitcoin-core-dev-theft",
          "publishedOn": "2024-04-12T09:59:41.000Z",
          "wordCount": 10152,
          "title": "FBI Subpoenas 2022 Event Attendees After Theft From Bitcoin Core Dev",
          "enclosure": {
            "url": "https://img.decrypt.co/insecure/rs:fill:1024:512:1:0/plain/https://cdn.decrypt.co/wp-content/uploads/2022/02/fbi-office-gID_7.jpeg@png",
            "length": "1000000",
            "type": "image/png"
          },
          "imageUrl": "https://img.decrypt.co/insecure/rs:fill:1024:512:1:0/plain/https://cdn.decrypt.co/wp-content/uploads/2022/02/fbi-office-gID_7.jpeg@png"
        },
        {
          "id": "https://decrypt.co/videos/interviews/LnaOT9bF/we-do-a-little-with-weesh",
          "author": null,
          "description": "In this week’s episode, we did a little something different. We took the man who is usually behind the camera and put him in front of it. We sat down with our producer Weesh to dive into how in fell in love with art and became a collector, how he met Andy and fun childhood memories together, his biggest wins in crypto, and so much more.",
          "link": "https://decrypt.co/videos/interviews/LnaOT9bF/we-do-a-little-with-weesh",
          "publishedOn": "2024-04-12T07:46:45.000Z",
          "wordCount": 6974,
          "title": "We Do A Little with Weesh",
          "enclosure": {
            "url": "https://cdn.jwplayer.com/v2/media/LnaOT9bF/poster.jpg",
            "length": "1000000",
            "type": "image/png"
          },
          "imageUrl": "https://cdn.jwplayer.com/v2/media/LnaOT9bF/poster.jpg"
        },
        {
          "id": "https://decrypt.co/?p=225979",
          "author": "Andrew Hayward",
          "description": "Notcoin’s conversion rate has been announced ahead of the token launch on The Open Network (TON).",
          "link": "https://decrypt.co/225979/how-many-notcoin-tokens-get-in-game-coins",
          "publishedOn": "2024-04-11T23:06:25.000Z",
          "wordCount": 10676,
          "title": "Here's How Many ‘Notcoin’ Tokens You'll Get for Your In-Game Coins",
          "enclosure": {
            "url": "https://img.decrypt.co/insecure/rs:fill:1024:512:1:0/plain/https://cdn.decrypt.co/wp-content/uploads/2024/04/notcoin-conversion-gID_7.png@png",
            "length": "1000000",
            "type": "image/png"
          },
          "imageUrl": "https://img.decrypt.co/insecure/rs:fill:1024:512:1:0/plain/https://cdn.decrypt.co/wp-content/uploads/2024/04/notcoin-conversion-gID_7.png@png"
        },
        {
          "id": "https://decrypt.co/?p=225971",
          "author": "Andrew Hayward",
          "description": "The BitBoy One and SuiPlay0x1 are coming to join the Solana Saga smartphone—a look at the portable crypto crypto gaming devices.",
          "link": "https://decrypt.co/225971/bitcoin-sui-solana-gaming-handhelds-preview",
          "publishedOn": "2024-04-11T22:20:11.000Z",
          "wordCount": 13032,
          "title": "Bitcoin, Sui and Solana Gaming Handhelds: Here's How They Stack Up",
          "enclosure": {
            "url": "https://img.decrypt.co/insecure/rs:fill:1024:512:1:0/plain/https://cdn.decrypt.co/wp-content/uploads/2024/04/crypto-gaming-handhelds-gID_7.png@png",
            "length": "1000000",
            "type": "image/png"
          },
          "imageUrl": "https://img.decrypt.co/insecure/rs:fill:1024:512:1:0/plain/https://cdn.decrypt.co/wp-content/uploads/2024/04/crypto-gaming-handhelds-gID_7.png@png"
        },
        {
          "id": "https://decrypt.co/?p=225885",
          "author": "Decrypt Staff",
          "description": "A collection of 9,999 spaceship NFTs for the third-person space combat and base management game go on sale from April 16th.",
          "link": "https://decrypt.co/225885/cinematic-space-combat-game-nova-frontier-x-counts-down-to-nft-launch",
          "publishedOn": "2024-04-11T20:51:20.000Z",
          "wordCount": 10645,
          "title": "‘Cinematic’ Space Combat Game Nova Frontier X Counts Down to NFT Launch",
          "enclosure": {
            "url": "https://img.decrypt.co/insecure/rs:fill:1024:512:1:0/plain/https://cdn.decrypt.co/wp-content/uploads/2024/04/nova-frontier-01-gID_7.jpg@png",
            "length": "1000000",
            "type": "image/png"
          },
          "imageUrl": "https://img.decrypt.co/insecure/rs:fill:1024:512:1:0/plain/https://cdn.decrypt.co/wp-content/uploads/2024/04/nova-frontier-01-gID_7.jpg@png"
        },
        {
          "id": "https://decrypt.co/?p=225953",
          "author": "Sander Lutz",
          "description": "The passing of OJ Simpson spawned another surge in meme coins. What's fueling the rising trend of celebrity death-inspired crypto tokens?",
          "link": "https://decrypt.co/225953/oj-simpson-queen-why-degens-meme-coins-celebrities-die",
          "publishedOn": "2024-04-11T20:37:24.000Z",
          "wordCount": 11071,
          "title": "From OJ to the Queen: Why Degens Rush to Create Meme Coins When Celebrities Die",
          "enclosure": {
            "url": "https://img.decrypt.co/insecure/rs:fill:1024:512:1:0/plain/https://cdn.decrypt.co/wp-content/uploads/2024/04/Degens-Only-gID_7.jpg@png",
            "length": "1000000",
            "type": "image/png"
          },
          "imageUrl": "https://img.decrypt.co/insecure/rs:fill:1024:512:1:0/plain/https://cdn.decrypt.co/wp-content/uploads/2024/04/Degens-Only-gID_7.jpg@png"
        },
        {
          "id": "https://decrypt.co/?p=225947",
          "author": "Jose Antonio Lanz",
          "description": "A potential IPO for Telegram has contributed to the recent surge in the price of TON, strengthening its position among the biggest tokens in crypto.",
          "link": "https://decrypt.co/225947/toncoin-ton-market-cap-flip-dogecoin-doge-ipo",
          "publishedOn": "2024-04-11T19:39:52.000Z",
          "wordCount": 10687,
          "title": "Toncoin Nearly Flips Dogecoin as TON Surges",
          "enclosure": {
            "url": "https://img.decrypt.co/insecure/rs:fill:1024:512:1:0/plain/https://cdn.decrypt.co/wp-content/uploads/2024/04/toncoin-shutterstock-gID_7.png@png",
            "length": "1000000",
            "type": "image/png"
          },
          "imageUrl": "https://img.decrypt.co/insecure/rs:fill:1024:512:1:0/plain/https://cdn.decrypt.co/wp-content/uploads/2024/04/toncoin-shutterstock-gID_7.png@png"
        },
        {
          "id": "https://decrypt.co/?p=225937",
          "author": "Mathew Di Salvo",
          "description": "The banking giant is the latest to lower its expectations regarding the SEC's review of proposals to offer funds tied to the price of ETH.",
          "link": "https://decrypt.co/225937/theres-a-50-chance-of-ethereum-etf-approval-next-month-jp-morgan",
          "publishedOn": "2024-04-11T19:13:34.000Z",
          "wordCount": 10297,
          "title": "There’s a 50% Chance of Ethereum ETF Approval Next Month: JP Morgan",
          "enclosure": {
            "url": "https://img.decrypt.co/insecure/rs:fill:1024:512:1:0/plain/https://cdn.decrypt.co/wp-content/uploads/2021/04/ethereum-etf-trading-markets-gID_7.jpg@png",
            "length": "1000000",
            "type": "image/png"
          },
          "imageUrl": "https://img.decrypt.co/insecure/rs:fill:1024:512:1:0/plain/https://cdn.decrypt.co/wp-content/uploads/2021/04/ethereum-etf-trading-markets-gID_7.jpg@png"
        },
        {
          "id": "https://decrypt.co/?p=225942",
          "author": "Chainwire",
          "description": "Metacade, the leading blockchain gaming platform, takes a monumental leap forward with the integration of multi-chains into its ecosystem.",
          "link": "https://decrypt.co/225942/metacade-unchains-web3-gaming-multi-chain-integration-unites-the-industry",
          "publishedOn": "2024-04-11T19:07:44.000Z",
          "wordCount": 9473,
          "title": "Metacade Unchains Web3 Gaming: Multi-Chain Integration Unites the Industry",
          "enclosure": {
            "url": "https://img.decrypt.co/insecure/rs:fill:1024:512:1:0/plain/https://cdn.decrypt.co/wp-content/uploads/2024/04/Metacade_-_Multi-Chain_Gaming_v2_17127631137TQq68teik-gID_7.jpg@png",
            "length": "1000000",
            "type": "image/png"
          },
          "imageUrl": "https://img.decrypt.co/insecure/rs:fill:1024:512:1:0/plain/https://cdn.decrypt.co/wp-content/uploads/2024/04/Metacade_-_Multi-Chain_Gaming_v2_17127631137TQq68teik-gID_7.jpg@png"
        },
        {
          "id": "https://decrypt.co/?p=225927",
          "author": "Mathew Di Salvo",
          "description": "Mining Bitcoin is now more difficult than ever before—just in time for the long-awaited halving event next week.",
          "link": "https://decrypt.co/225927/bitcoin-mining-difficulty-all-time-high-halving",
          "publishedOn": "2024-04-11T17:14:09.000Z",
          "wordCount": 9565,
          "title": "Bitcoin Mining Difficulty Hits All-Time High One Week Before Halving",
          "enclosure": {
            "url": "https://img.decrypt.co/insecure/rs:fill:1024:512:1:0/plain/https://cdn.decrypt.co/wp-content/uploads/2023/09/bitcoin-btc-mining-hashrate-token-gID_7.jpg@png",
            "length": "1000000",
            "type": "image/png"
          },
          "imageUrl": "https://img.decrypt.co/insecure/rs:fill:1024:512:1:0/plain/https://cdn.decrypt.co/wp-content/uploads/2023/09/bitcoin-btc-mining-hashrate-token-gID_7.jpg@png"
        },
        {
          "id": "https://decrypt.co/?p=225923",
          "author": "Andrew Throuvalas",
          "description": "Grayscale’s Bitcoin outflows slowed on Wednesday, though on-chain analysis suggests the fund may still bleed coins for the duration of the bull market.",
          "link": "https://decrypt.co/225923/grayscale-bitcoin-trust-withdrawals-record-low-selling-stopped",
          "publishedOn": "2024-04-11T16:33:45.000Z",
          "wordCount": 10498,
          "title": "Grayscale Bitcoin Trust Withdrawals Hit Record Low—Has the Selling Stopped?",
          "enclosure": {
            "url": "https://img.decrypt.co/insecure/rs:fill:1024:512:1:0/plain/https://cdn.decrypt.co/wp-content/uploads/2022/12/grayscale-bitcoin-trust-gID_7.jpg@png",
            "length": "1000000",
            "type": "image/png"
          },
          "imageUrl": "https://img.decrypt.co/insecure/rs:fill:1024:512:1:0/plain/https://cdn.decrypt.co/wp-content/uploads/2022/12/grayscale-bitcoin-trust-gID_7.jpg@png"
        },
        {
          "id": "https://decrypt.co/?p=225904",
          "author": "Ryan Gladwin",
          "description": "Oracle provider, Chainlink, is connecting the blockchain with a new cross-chain bridging app promising “unmatched” security.",
          "link": "https://decrypt.co/225904/chainlink-transporter-to-bridge-assets-across-ethereum-optimism-base-and-more",
          "publishedOn": "2024-04-11T16:01:03.000Z",
          "wordCount": 10341,
          "title": "Chainlink Transporter to Bridge Assets Across Ethereum, Optimism, Base and More",
          "enclosure": {
            "url": "https://img.decrypt.co/insecure/rs:fill:1024:512:1:0/plain/https://cdn.decrypt.co/wp-content/uploads/2020/06/chainlink-kyber-network-defi-gID_7.jpg@png",
            "length": "1000000",
            "type": "image/png"
          },
          "imageUrl": "https://img.decrypt.co/insecure/rs:fill:1024:512:1:0/plain/https://cdn.decrypt.co/wp-content/uploads/2020/06/chainlink-kyber-network-defi-gID_7.jpg@png"
        },
        {
          "id": "https://decrypt.co/?p=223640",
          "author": "Reza Jafery,Andrew Hayward",
          "description": "UPDATED: The NOT token is set to launch in just over a week, and we have details about what will happen to Notcoin after that.",
          "link": "https://decrypt.co/resources/what-is-notcoin-telegram-based-game-airdrop",
          "publishedOn": "2024-04-11T15:07:28.000Z",
          "wordCount": 13897,
          "title": "What Is Notcoin? The Telegram-Based Game, NOT Token, and Future Plans",
          "enclosure": {
            "url": "https://img.decrypt.co/insecure/rs:fill:1024:512:1:0/plain/https://cdn.decrypt.co/wp-content/uploads/2019/03/gaming_litepaper-gID_7-pID_3.png@png",
            "length": "1000000",
            "type": "image/png"
          },
          "imageUrl": "https://img.decrypt.co/insecure/rs:fill:1024:512:1:0/plain/https://cdn.decrypt.co/wp-content/uploads/2019/03/gaming_litepaper-gID_7-pID_3.png@png"
        },
        {
          "id": "https://decrypt.co/videos/interviews/9YAY4wGD/inside-vanecks-crypto-takeover-of-the-new-york-stock-exchange",
          "author": null,
          "description": "Worlds collide as Decrypt reporter Sander Lutz heads to the floor of the NYSE to witness a special closing bell ceremony hosted by VanEck in honor of Web3. Featuring Choose Rich Nick, VanEck Head of Web3 Matt Bartlett, and more!",
          "link": "https://decrypt.co/videos/interviews/9YAY4wGD/inside-vanecks-crypto-takeover-of-the-new-york-stock-exchange",
          "publishedOn": "2024-04-11T14:40:00.000Z",
          "wordCount": 6868,
          "title": "Inside VanEck’s Crypto Takeover of the New York Stock Exchange",
          "enclosure": {
            "url": "https://cdn.jwplayer.com/v2/media/9YAY4wGD/poster.jpg",
            "length": "1000000",
            "type": "image/png"
          },
          "imageUrl": "https://cdn.jwplayer.com/v2/media/9YAY4wGD/poster.jpg"
        },
        {
          "id": "https://decrypt.co/videos/interviews/9SNiIVfU/wormhole-wednesday",
          "author": null,
          "description": "BTC hits $64.5K then rebounds, SOL outperforms. Government sends $2B BTC to Coinbase to sell. Funding rates stay low after sweep lower. ETFs see small inflow, Ark outflow more than GBTC. Wormhole W launches at $15B FDV. BTC ‘inflection point’ if it follows rates or gold. Gold & BTC very correlated for the last year. Expect slower ETF volume this month: Bloomberg. BTC 2x and 3x levered ETFs launch yesterday. BTC ETFs now half the size of gold.",
          "link": "https://decrypt.co/videos/interviews/9SNiIVfU/wormhole-wednesday",
          "publishedOn": "2024-04-07T17:42:37.000Z",
          "wordCount": 7010,
          "title": "Wormhole Wednesday",
          "enclosure": {
            "url": "https://cdn.jwplayer.com/v2/media/9SNiIVfU/poster.jpg",
            "length": "1000000",
            "type": "image/png"
          },
          "imageUrl": "https://cdn.jwplayer.com/v2/media/9SNiIVfU/poster.jpg"
        },
        {
          "id": "https://decrypt.co/videos/interviews/2KrbCFNp/first-dogs-now-cats",
          "author": null,
          "description": "BTC falls another 6% amid $400m liquidations. ETF outflows and dollar strength blamed for move. Funding completely reset to lows in move. BTC lower high leaves market in ‘no trade zone’. This cycle acting ‘nothing like previous cycle’. ETH unlikely to be classed a security: Coinbase CFO. Crypto VC funding up 53% in MarchAnsem’s cat coin sees more volume than NFT market. Most memecoins down 10-20% given move in majors. MEW up 10% after HTX lists, airdrop to Saga phones. MEME to launch memecoin chain, NFTs rise. Pixelmon releases trailer for Anime series.",
          "link": "https://decrypt.co/videos/interviews/2KrbCFNp/first-dogs-now-cats",
          "publishedOn": "2024-04-03T14:06:05.000Z",
          "wordCount": 7097,
          "title": "First Dogs, Now Cats",
          "enclosure": {
            "url": "https://cdn.jwplayer.com/v2/media/2KrbCFNp/poster.jpg",
            "length": "1000000",
            "type": "image/png"
          },
          "imageUrl": "https://cdn.jwplayer.com/v2/media/2KrbCFNp/poster.jpg"
        },
        {
          "id": "https://decrypt.co/videos/interviews/jSsgl6SQ/we-do-a-little-with-spencer-gordon-sand",
          "author": null,
          "description": "In this week’s episode, we sit down with Spencer Gordon Sand, the mastermind behind Spencer Ventures. Before launching Spencer Ventures, Spencer was a competitive fencer, Magic the gathering player, and startup enjoyooor. \n\nWe dive into Spencer’s investment thesis behind NFTs and how his fund invests, finding and buying distressed assets in a bear market , point farming optimization, a peak behind the 3AC liquidation and dickbutt buys, and so much more.",
          "link": "https://decrypt.co/videos/interviews/jSsgl6SQ/we-do-a-little-with-spencer-gordon-sand",
          "publishedOn": "2024-03-29T17:11:12.000Z",
          "wordCount": 7005,
          "title": "We Do A Little With Spencer Gordon-Sand",
          "enclosure": {
            "url": "https://cdn.jwplayer.com/v2/media/jSsgl6SQ/poster.jpg",
            "length": "1000000",
            "type": "image/png"
          },
          "imageUrl": "https://cdn.jwplayer.com/v2/media/jSsgl6SQ/poster.jpg"
        },
        {
          "id": "https://decrypt.co/videos/interviews/d8FYP5tO/how-to-get-your-foot-in-ihe-door-and-building-during-bear-markets",
          "author": null,
          "description": "In this week’s episode, we sit down with Intern and Tunez from the Monad team. Prior to Monad, Tunez was working with Delphi Digital and Intern was working at CMS Holdings. They’re two of my oldest friends from crypto twitter.\n\nWe get into why they joined the Monad team, alpha for finding jobs in the space, biggest lessons from previous cycles, and so much more.",
          "link": "https://decrypt.co/videos/interviews/d8FYP5tO/how-to-get-your-foot-in-ihe-door-and-building-during-bear-markets",
          "publishedOn": "2024-03-29T11:37:20.000Z",
          "wordCount": 7008,
          "title": "How To Get Your Foot In Ihe Door And Building During Bear Markets",
          "enclosure": {
            "url": "https://cdn.jwplayer.com/v2/media/d8FYP5tO/poster.jpg",
            "length": "1000000",
            "type": "image/png"
          },
          "imageUrl": "https://cdn.jwplayer.com/v2/media/d8FYP5tO/poster.jpg"
        },
        {
          "id": "https://decrypt.co/videos/interviews/ZmRslhIl/sbf-sentencing",
          "author": null,
          "description": "BTC: 70.7k (+1%), ETH: 3585 (0%), SOL: 186 (-1%). Top 100 gainers: DOGE, GT, BCH, RBN. Crypto mixed, BTC-beta & memes outperform. SEC case vs Coinbase set to go to trial. DeFi win as case dismissed vs Coinbase wallet. ETFs see $244m inflows led by Ark. BlackRock ETF fastest growing in history: Fink. ETH ETF possible even if its a security: Fink. ETH spot ETF by May chances only 20%: GSR. SBF sentencing today, faces 50 years.",
          "link": "https://decrypt.co/videos/interviews/ZmRslhIl/sbf-sentencing",
          "publishedOn": "2024-03-29T11:29:59.000Z",
          "wordCount": 7005,
          "title": "SBF Sentencing",
          "enclosure": {
            "url": "https://cdn.jwplayer.com/v2/media/ZmRslhIl/poster.jpg",
            "length": "1000000",
            "type": "image/png"
          },
          "imageUrl": "https://cdn.jwplayer.com/v2/media/ZmRslhIl/poster.jpg"
        },
        {
          "id": "https://decrypt.co/videos/interviews/l2sy2ZQY/the-63-million-exploit",
          "author": null,
          "description": "BTC consolidates around $70k, funding still low. ETFs see $418m inflow as GBTC outflow tiny. BTC set to have record 7th-straight green month. AI coins soar, FET hits ATH amid merger rumour. FET, OCEAN, AGIX token proposed at $7.5bn FDV. DoJ charges KuCoin over money laundering. KuCoin sees $800m outflows after charges. CFTC names ETH & LTC commodities in charges. HK set to allow ‘in-kind’ style ETFs. HSBC launches tokenised gold fund. Fidelity files S1 form for ETH ETF. Short sellers bet $11bn crypto rally won’t last. More customer USDC balances to be stored on Base.",
          "link": "https://decrypt.co/videos/interviews/l2sy2ZQY/the-63-million-exploit",
          "publishedOn": "2024-03-28T16:42:17.000Z",
          "wordCount": 7112,
          "title": "The $63 Million Exploit",
          "enclosure": {
            "url": "https://cdn.jwplayer.com/v2/media/l2sy2ZQY/poster.jpg",
            "length": "1000000",
            "type": "image/png"
          },
          "imageUrl": "https://cdn.jwplayer.com/v2/media/l2sy2ZQY/poster.jpg"
        },
        {
          "id": "https://decrypt.co/videos/interviews/1t8j4uWb/btc-is-back-on-top",
          "author": null,
          "description": "BTC breaks $70K as $175M of shorts liquidated. ETFs see net inflow despite high GBTC outflows. Gold miner set to buy $1.7B BTC. UK to list crypto ETNs in May. ETH ETF may still be approved: Grayscale. Grayscale ETH discount falls to 22%. ETH ETF has no positive signs: Bloomberg. Coinbase pumps 10%, Ark continue to sell shares. Coinbase Int. record trading volumes in March. FTX to sell majority of Anthropic stake for $884M. Trader makes $20m profit in MEW rally. Puppets hit ATH, lead move higher in Ordinals. Azuki flips MAYC market cap in bounce. Magic Eden makes $15m in 30d trading revenue.",
          "link": "https://decrypt.co/videos/interviews/1t8j4uWb/btc-is-back-on-top",
          "publishedOn": "2024-03-28T16:16:58.000Z",
          "wordCount": 7158,
          "title": "BTC Is Back On Top",
          "enclosure": {
            "url": "https://cdn.jwplayer.com/v2/media/1t8j4uWb/poster.jpg",
            "length": "1000000",
            "type": "image/png"
          },
          "imageUrl": "https://cdn.jwplayer.com/v2/media/1t8j4uWb/poster.jpg"
        },
        {
          "id": "https://decrypt.co/videos/interviews/OGLEeanX/base-on-top",
          "author": null,
          "description": "Majors continue to rally as ETF sentiment improves. Genesis have likely sold half their GBTC position. BlackRock could flip GBTC holdings in 3 weeks. BTC short squeeze would liquidate $6.6bn by $75k. Lack of on-chain activity indicates ‘limited selling’. BTC crucial to the financial system: BlackRock. Resurging interest in crypto assets: Goldman Sachs. Crypto summer has started: Raoul Pal. Base outpaces SOL & ETH for trading volumes.",
          "link": "https://decrypt.co/videos/interviews/OGLEeanX/base-on-top",
          "publishedOn": "2024-03-28T15:05:33.000Z",
          "wordCount": 7127,
          "title": "Base On Top",
          "enclosure": {
            "url": "https://cdn.jwplayer.com/v2/media/OGLEeanX/poster.jpg",
            "length": "1000000",
            "type": "image/png"
          },
          "imageUrl": "https://cdn.jwplayer.com/v2/media/OGLEeanX/poster.jpg"
        },
        {
          "id": "https://decrypt.co/videos/interviews/KGf7k2r3/etf-outflows-continue",
          "author": null,
          "description": "Despite Bitcoin's decline, several alternative cryptocurrencies remain robust. Fantom (FTM) emerges as the top-performing Layer 1 blockchain, while Coinbase introduces futures trading. Exchange-traded funds (ETFs) witness a $94 million outflow, although outflows from Grayscale Bitcoin Trust (GBTC) may decelerate. Approximately $1 billion worth of Bitcoin shorts face liquidation if prices reach $67.8k. Coinbase's premium resurfaces, marking the first occurrence since Bitcoin's all-time high. Bitcoin continues its streak with seven consecutive months of positive performance. Solana's (SOL) decentralized exchange (DEX) achieves a monthly volume of $50 billion, with revenue soaring 30-fold. OKX announces support for a new Solana token standard. Despite expectations, Layer 2 activity remains sluggish post-Dencun, according to Vitalik Buterin.",
          "link": "https://decrypt.co/videos/interviews/KGf7k2r3/etf-outflows-continue",
          "publishedOn": "2024-03-22T17:56:30.000Z",
          "wordCount": 7181,
          "title": "ETF Outflows Continue",
          "enclosure": {
            "url": "https://cdn.jwplayer.com/v2/media/KGf7k2r3/poster.jpg",
            "length": "1000000",
            "type": "image/png"
          },
          "imageUrl": "https://cdn.jwplayer.com/v2/media/KGf7k2r3/poster.jpg"
        },
        {
          "id": "https://decrypt.co/videos/interviews/DFwsnxwz/we-do-a-little-with-postwook",
          "author": null,
          "description": "In this week’s episode, we sit down with Natasha Chomko aka Postwook. Postwook is a Los Angeles based digital artist focused on cooking up some of the most visually pleasing and nostalgia provoking surreal landscape collage art.\n\nWe dive into Postwook’s origin story, training like an athlete as an artist, diversifying income streams, beating addiction, dealing with the ebbs and flows of being a full time artist in a volatile space, and so much more.",
          "link": "https://decrypt.co/videos/interviews/DFwsnxwz/we-do-a-little-with-postwook",
          "publishedOn": "2024-03-22T10:12:08.000Z",
          "wordCount": 7016,
          "title": "We Do A Little With Postwook",
          "enclosure": {
            "url": "https://cdn.jwplayer.com/v2/media/DFwsnxwz/poster.jpg",
            "length": "1000000",
            "type": "image/png"
          },
          "imageUrl": "https://cdn.jwplayer.com/v2/media/DFwsnxwz/poster.jpg"
        },
        {
          "id": "https://decrypt.co/videos/interviews/NX2FxOu0/scaling-ethereum-and-aligning-incentives-with-the-chief-strategic-officer-of-offchain-labs",
          "author": null,
          "description": "In this episode, we are joined by AJ Warner, the Chief Strategic Officer of Offchain Labs, the main contributors to the Arbitrum ecosystem. AJ is a gigabrain chad who joined the Offchain Labs in November 2020 and has been their CSO since January 2022.\n\n\nWe dive into AJ’s crypto origin story, how he joined Offchain Labs, the technical and ideological differences between Arbitrum and other scaling solutions, how the scaling solution business model works, the biggest blockers in crypto as investors and builders, and so much more.",
          "link": "https://decrypt.co/videos/interviews/NX2FxOu0/scaling-ethereum-and-aligning-incentives-with-the-chief-strategic-officer-of-offchain-labs",
          "publishedOn": "2024-03-22T09:47:06.000Z",
          "wordCount": 7118,
          "title": "Scaling Ethereum and Aligning Incentives with the Chief Strategic Officer of Offchain Labs",
          "enclosure": {
            "url": "https://cdn.jwplayer.com/v2/media/NX2FxOu0/poster.jpg",
            "length": "1000000",
            "type": "image/png"
          },
          "imageUrl": "https://cdn.jwplayer.com/v2/media/NX2FxOu0/poster.jpg"
        },
        {
          "id": "https://decrypt.co/videos/interviews/jM2FTmnm/founding-the-nifty-bodoggos-learnings-from-multiple-years-of-hosting-daily-shows-and-leveling-up-the-crypto-content-industry",
          "author": null,
          "description": "Starting Season 4 of We Do A Little with a great interview featuring Nick and Pio from The Nifty and BoDoggos.\n\nAlongside developing their business and identity, they have consistently delivered entertaining morning shows and humorous content centered around the crypto.\n\nIn this episode, we delve into Nick and Pio’s backgrounds prior to collaborating, explore the story of their meeting, discuss their individual sources of inspiration, examine their strategic approach to expanding the Nifty team, and much more.",
          "link": "https://decrypt.co/videos/interviews/jM2FTmnm/founding-the-nifty-bodoggos-learnings-from-multiple-years-of-hosting-daily-shows-and-leveling-up-the-crypto-content-industry",
          "publishedOn": "2024-03-21T18:03:15.000Z",
          "wordCount": 7112,
          "title": "Founding The Nifty & BoDoggos, learnings from multiple years of hosting daily shows, and leveling up the crypto content industry",
          "enclosure": {
            "url": "https://cdn.jwplayer.com/v2/media/jM2FTmnm/poster.jpg",
            "length": "1000000",
            "type": "image/png"
          },
          "imageUrl": "https://cdn.jwplayer.com/v2/media/jM2FTmnm/poster.jpg"
        },
        {
          "id": "https://decrypt.co/videos/interviews/LPwwmRJP/vitalik-buterin-discusses-ethereums-dencun-upgrade-and-more-at-eth-taipei-2024",
          "author": null,
          "description": "Ethereum creator Vitalik Buterin answers questions from Rug Radio and other media outlets at ETH Taipei 2024. He discusses the recent Dencun network upgrade and a variety of other topics. (Credit: Rug Radio/Decrypt)",
          "link": "https://decrypt.co/videos/interviews/LPwwmRJP/vitalik-buterin-discusses-ethereums-dencun-upgrade-and-more-at-eth-taipei-2024",
          "publishedOn": "2024-03-21T14:39:50.000Z",
          "wordCount": 6845,
          "title": "Vitalik Buterin Discusses Ethereum's Dencun Upgrade and More at ETH Taipei 2024",
          "enclosure": {
            "url": "https://cdn.jwplayer.com/v2/media/LPwwmRJP/poster.jpg",
            "length": "1000000",
            "type": "image/png"
          },
          "imageUrl": "https://cdn.jwplayer.com/v2/media/LPwwmRJP/poster.jpg"
        },
        {
          "id": "https://decrypt.co/videos/interviews/RGxNjELq/the-weekend-madness",
          "author": null,
          "description": "Bitcoin rebounds as users withdraw funds from exchanges. Solana breaks $200, surpassing Binance Coin to claim the 4th spot in crypto rankings. Ethereum's supply drops to a two-year low. Over $100 million raised by new coin presales in just two days. A dog NFT sells for a staggering $4.3 million. PRIME emerges as the leader in gaming coins, while NodeMonkes flips Bored Ape Yacht Club (BAYC).",
          "link": "https://decrypt.co/videos/interviews/RGxNjELq/the-weekend-madness",
          "publishedOn": "2024-03-19T09:59:27.000Z",
          "wordCount": 6956,
          "title": "The Weekend Madness",
          "enclosure": {
            "url": "https://cdn.jwplayer.com/v2/media/RGxNjELq/poster.jpg",
            "length": "1000000",
            "type": "image/png"
          },
          "imageUrl": "https://cdn.jwplayer.com/v2/media/RGxNjELq/poster.jpg"
        },
        {
          "id": "https://decrypt.co/videos/interviews/wiIrxdqG/bome-blast-off",
          "author": null,
          "description": "BTC experiences a 9% drop, resulting in $700 million liquidations, with funding and open interest hitting their lowest levels in weeks. The sell-off appears more sustained compared to previous brief dips, with most BTC downside liquidations concentrated around $66,000. ETFs witness $132 million inflows, sparking predictions of a potential liquidity crisis within six months. VanEck suggests that an ETH ETF could surpass BTC in size. Grayscale's ETH discount doubles within a week. Meanwhile, SOL's market cap reaches an all-time high amid a frenzy surrounding memecoins. Additionally, rumors circulate about a fund losing $1 billion on the BTC-MicroStrategy basis.",
          "link": "https://decrypt.co/videos/interviews/wiIrxdqG/bome-blast-off",
          "publishedOn": "2024-03-18T14:11:23.000Z",
          "wordCount": 7116,
          "title": "BOME Blast off",
          "enclosure": {
            "url": "https://cdn.jwplayer.com/v2/media/wiIrxdqG/poster.jpg",
            "length": "1000000",
            "type": "image/png"
          },
          "imageUrl": "https://cdn.jwplayer.com/v2/media/wiIrxdqG/poster.jpg"
        }
      ]
    }
  ],
  "cliVersion": "1.15.1"
}