{
  "sources": [
    {
      "title": "Decrypt",
      "feedUrl": "https://decrypt.co/feed",
      "siteUrl": "https://decrypt.co/feed",
      "articles": [
        {
          "id": "https://decrypt.co/?p=154729",
          "author": "Jason Nelson",
          "description": "Following a successful $140 million Series C fundraise, Oxa is set to debut its driverless shuttles in Florida.",
          "link": "https://decrypt.co/154729/oxa-startup-using-ai-to-improve-morning-commute",
          "publishedOn": "2023-09-02T20:53:08.000Z",
          "wordCount": 9427,
          "title": "This Startup Wants to Use AI to Improve Your Morning Commute",
          "enclosure": {
            "url": "https://img.decrypt.co/insecure/rs:fill:1024:512:1:0/plain/https://cdn.decrypt.co/wp-content/uploads/2023/09/Beep-Oxa-16x9-1-gID_7.jpg@png",
            "length": "1000000",
            "type": "image/png"
          },
          "imageUrl": "https://img.decrypt.co/insecure/rs:fill:1024:512:1:0/plain/https://cdn.decrypt.co/wp-content/uploads/2023/09/Beep-Oxa-16x9-1-gID_7.jpg@png"
        },
        {
          "id": "https://decrypt.co/?p=154724",
          "author": "Alyssa Hertig",
          "description": "KuCoin says crypto adoption is high in Turkey, as observed in other nations struggling with rapid inflation.",
          "link": "https://decrypt.co/154724/republic-of-turkey-crypto-adoption-half-kucoin",
          "publishedOn": "2023-09-02T20:32:30.000Z",
          "wordCount": 8552,
          "title": "Half of the People in Turkey Now Own Crypto: Report",
          "enclosure": {
            "url": "https://img.decrypt.co/insecure/rs:fill:1024:512:1:0/plain/https://cdn.decrypt.co/wp-content/uploads/2023/09/Turkey-shutterstock_1937455486-gID_7.jpg@png",
            "length": "1000000",
            "type": "image/png"
          },
          "imageUrl": "https://img.decrypt.co/insecure/rs:fill:1024:512:1:0/plain/https://cdn.decrypt.co/wp-content/uploads/2023/09/Turkey-shutterstock_1937455486-gID_7.jpg@png"
        },
        {
          "id": "https://decrypt.co/?p=154705",
          "author": "Jason Nelson",
          "description": "The modern twist on the 900 numbers of the past, AI chatbots provide interactive conversations.",
          "link": "https://decrypt.co/154705/here-are-the-ai-celebrities-you-can-date-right-now",
          "publishedOn": "2023-09-02T19:12:35.000Z",
          "wordCount": 10650,
          "title": "Here Are The AI Celebrities You Can Date Right Now",
          "enclosure": {
            "url": "https://img.decrypt.co/insecure/rs:fill:1024:512:1:0/plain/https://cdn.decrypt.co/wp-content/uploads/2023/09/1-900-Mix-a-Lot-RKO-gID_7.jpg@png",
            "length": "1000000",
            "type": "image/png"
          },
          "imageUrl": "https://img.decrypt.co/insecure/rs:fill:1024:512:1:0/plain/https://cdn.decrypt.co/wp-content/uploads/2023/09/1-900-Mix-a-Lot-RKO-gID_7.jpg@png"
        },
        {
          "id": "https://decrypt.co/?p=154695",
          "author": "Tim Hakki",
          "description": "Also, the SEC was ordered to review its denial of crypto asset manager Grayscale’s ETF proposal.",
          "link": "https://decrypt.co/154695/this-week-in-coins-bitcoin-ethereum-toncoin-ton-polygon-matic",
          "publishedOn": "2023-09-02T17:08:31.000Z",
          "wordCount": 8747,
          "title": "This Week in Coins: Bitcoin and Ethereum Unmoved in Slow Market Week",
          "enclosure": {
            "url": "https://img.decrypt.co/insecure/rs:fill:1024:512:1:0/plain/https://cdn.decrypt.co/wp-content/uploads/2023/09/Bitcoin-Ethereum-jars-shutterstock_1023144148-16x9-1-gID_7.jpg@png",
            "length": "1000000",
            "type": "image/png"
          },
          "imageUrl": "https://img.decrypt.co/insecure/rs:fill:1024:512:1:0/plain/https://cdn.decrypt.co/wp-content/uploads/2023/09/Bitcoin-Ethereum-jars-shutterstock_1023144148-16x9-1-gID_7.jpg@png"
        },
        {
          "id": "https://decrypt.co/?p=154658",
          "author": "Kate Irwin",
          "description": "Summer is over, but the games are still coming. From Starfield to Final Fantasy, here are the biggest video games releasing in September.",
          "link": "https://decrypt.co/154658/biggest-video-games-releasing-september-2023",
          "publishedOn": "2023-09-02T17:03:38.000Z",
          "wordCount": 10678,
          "title": "Biggest Video Games Releasing in September 2023",
          "enclosure": {
            "url": "https://img.decrypt.co/insecure/rs:fill:1024:512:1:0/plain/https://cdn.decrypt.co/wp-content/uploads/2023/09/starfield-art-gID_7.jpeg@png",
            "length": "1000000",
            "type": "image/png"
          },
          "imageUrl": "https://img.decrypt.co/insecure/rs:fill:1024:512:1:0/plain/https://cdn.decrypt.co/wp-content/uploads/2023/09/starfield-art-gID_7.jpeg@png"
        },
        {
          "id": "https://decrypt.co/?p=154566",
          "author": "Liam J. Kelly",
          "description": "With more than $3.3 million in profit generated since its mainnet launch on August 9, the Base network is firing on all cylinders.",
          "link": "https://decrypt.co/154566/base-network-rakes-fees-riding-cryptos-favorite-memes",
          "publishedOn": "2023-09-02T10:01:02.000Z",
          "wordCount": 9138,
          "title": "Base Network Rakes in the Fees Riding Crypto's Favorite Memes",
          "enclosure": {
            "url": "https://img.decrypt.co/insecure/rs:fill:1024:512:1:0/plain/https://cdn.decrypt.co/wp-content/uploads/2023/07/Base-16x9-1-gID_7.jpg@png",
            "length": "1000000",
            "type": "image/png"
          },
          "imageUrl": "https://img.decrypt.co/insecure/rs:fill:1024:512:1:0/plain/https://cdn.decrypt.co/wp-content/uploads/2023/07/Base-16x9-1-gID_7.jpg@png"
        },
        {
          "id": "https://decrypt.co/?p=154663",
          "author": "Mathew Di Salvo",
          "description": "FTX’s new management is starting to move its holdings around. Amid fears of an impending dump, a Solana co-founder has an idea.",
          "link": "https://decrypt.co/154663/solana-cofounder-says-ftx-sol-should-distributed-customers",
          "publishedOn": "2023-09-01T22:32:57.000Z",
          "wordCount": 9127,
          "title": "Solana Co-Founder Says FTX's SOL Should Be Distributed to Customers",
          "enclosure": {
            "url": "https://img.decrypt.co/insecure/rs:fill:1024:512:1:0/plain/https://cdn.decrypt.co/wp-content/uploads/2023/06/solana-tokens-sol-gID_7.jpg@png",
            "length": "1000000",
            "type": "image/png"
          },
          "imageUrl": "https://img.decrypt.co/insecure/rs:fill:1024:512:1:0/plain/https://cdn.decrypt.co/wp-content/uploads/2023/06/solana-tokens-sol-gID_7.jpg@png"
        },
        {
          "id": "https://decrypt.co/?p=154664",
          "author": "Jose Antonio Lanz",
          "description": "Psilocybin is having a magical effect on major depression disorders, but more study is needed, new research suggests.",
          "link": "https://decrypt.co/154664/depression-treatment-psychedelic-psilocybin-mushrooms",
          "publishedOn": "2023-09-01T21:35:09.000Z",
          "wordCount": 9707,
          "title": "Just One Dose of Magic Mushroom Psychedelic Can Ease Depression for Weeks, Study Finds",
          "enclosure": {
            "url": "https://img.decrypt.co/insecure/rs:fill:1024:512:1:0/plain/https://cdn.decrypt.co/wp-content/uploads/2023/09/jaldps_a_magic_garden_full_of_mushrooms_vivid_colors_psychedeli_dee27d74-85d0-4126-930b-694644d0c153-gID_7.png@png",
            "length": "1000000",
            "type": "image/png"
          },
          "imageUrl": "https://img.decrypt.co/insecure/rs:fill:1024:512:1:0/plain/https://cdn.decrypt.co/wp-content/uploads/2023/09/jaldps_a_magic_garden_full_of_mushrooms_vivid_colors_psychedeli_dee27d74-85d0-4126-930b-694644d0c153-gID_7.png@png"
        },
        {
          "id": "https://decrypt.co/?p=154656",
          "author": "André Beganski",
          "description": "Robinhood shares jumped 3% following news of the buy back.",
          "link": "https://decrypt.co/154656/robinhood-buys-back-sam-bankman-fried-seized-shares",
          "publishedOn": "2023-09-01T18:42:13.000Z",
          "wordCount": 8917,
          "title": "Robinhood Buys Back Sam Bankman-Fried’s Seized Shares Worth $600 Million",
          "enclosure": {
            "url": "https://img.decrypt.co/insecure/rs:fill:1024:512:1:0/plain/https://cdn.decrypt.co/wp-content/uploads/2020/07/robinhood-app-crypto-trading-uk-launch-gID_7.jpg@png",
            "length": "1000000",
            "type": "image/png"
          },
          "imageUrl": "https://img.decrypt.co/insecure/rs:fill:1024:512:1:0/plain/https://cdn.decrypt.co/wp-content/uploads/2020/07/robinhood-app-crypto-trading-uk-launch-gID_7.jpg@png"
        },
        {
          "id": "https://decrypt.co/?p=154651",
          "author": "André Beganski",
          "description": "A district judge's recent decision in a class action lawsuit against Uniswap demarcates DeFi from centralized exchanges like Coinbase.",
          "link": "https://decrypt.co/154651/uniswap-ruling-creates-regulatory-anomaly-defi-legal-scholar",
          "publishedOn": "2023-09-01T18:19:03.000Z",
          "wordCount": 9734,
          "title": "Uniswap Ruling Creates Regulatory 'Anomaly' for DeFi: Legal Scholar",
          "enclosure": {
            "url": "https://img.decrypt.co/insecure/rs:fill:1024:512:1:0/plain/https://cdn.decrypt.co/wp-content/uploads/2023/06/uniswap-uni-coin-on-laptop-keyboard-gID_7.jpg@png",
            "length": "1000000",
            "type": "image/png"
          },
          "imageUrl": "https://img.decrypt.co/insecure/rs:fill:1024:512:1:0/plain/https://cdn.decrypt.co/wp-content/uploads/2023/06/uniswap-uni-coin-on-laptop-keyboard-gID_7.jpg@png"
        },
        {
          "id": "https://decrypt.co/?p=154618",
          "author": "Jose Antonio Lanz",
          "description": "With new features in Automatic 1111 and InvokeAI's latest versions, the Stable Diffusion platforms are easier and more powerful.",
          "link": "https://decrypt.co/154618/the-two-most-popular-stable-diffusion-uis-just-got-major-upgrades",
          "publishedOn": "2023-09-01T17:20:41.000Z",
          "wordCount": 8797,
          "title": "The Two Most Popular Stable Diffusion UIs Just Got Major Upgrades",
          "enclosure": {
            "url": "https://img.decrypt.co/insecure/rs:fill:1024:512:1:0/plain/https://cdn.decrypt.co/wp-content/uploads/2023/09/00004-478042937-gID_7.png@png",
            "length": "1000000",
            "type": "image/png"
          },
          "imageUrl": "https://img.decrypt.co/insecure/rs:fill:1024:512:1:0/plain/https://cdn.decrypt.co/wp-content/uploads/2023/09/00004-478042937-gID_7.png@png"
        },
        {
          "id": "https://decrypt.co/?p=153493",
          "author": "André Beganski",
          "description": "Manhattan's Seaport neighborhood is hosting a scavenger hunt driven by NFTs and QR codes, but it wasn't all smooth sailing at first.",
          "link": "https://decrypt.co/153493/nyc-seaport-scavenger-hunt-brings-nfts-real-world",
          "publishedOn": "2023-09-01T17:19:28.000Z",
          "wordCount": 11416,
          "title": "NYC Seaport Scavenger Hunt Brings NFTs Into the Real World",
          "enclosure": {
            "url": "https://img.decrypt.co/insecure/rs:fill:1024:512:1:0/plain/https://cdn.decrypt.co/wp-content/uploads/2023/08/DSCF7476-2-scaled-gID_7.jpg@png",
            "length": "1000000",
            "type": "image/png"
          },
          "imageUrl": "https://img.decrypt.co/insecure/rs:fill:1024:512:1:0/plain/https://cdn.decrypt.co/wp-content/uploads/2023/08/DSCF7476-2-scaled-gID_7.jpg@png"
        },
        {
          "id": "https://decrypt.co/?p=154608",
          "author": "Mathew Di Salvo",
          "description": "For most of 2022, USDC was close to catching its rival Tether. But that figure has been shrinking—and fast.",
          "link": "https://decrypt.co/154608/shinking-market-share-circle-usdc-stablecoin",
          "publishedOn": "2023-09-01T17:07:28.000Z",
          "wordCount": 9869,
          "title": "The Incredible Shrinking Market Share of Circle’s USDC Stablecoin",
          "enclosure": {
            "url": "https://img.decrypt.co/insecure/rs:fill:1024:512:1:0/plain/https://cdn.decrypt.co/wp-content/uploads/2023/09/usdc-usd-coin-stablecoin-circle-gID_7.jpg@png",
            "length": "1000000",
            "type": "image/png"
          },
          "imageUrl": "https://img.decrypt.co/insecure/rs:fill:1024:512:1:0/plain/https://cdn.decrypt.co/wp-content/uploads/2023/09/usdc-usd-coin-stablecoin-circle-gID_7.jpg@png"
        },
        {
          "id": "https://decrypt.co/?p=154542",
          "author": "Sander Lutz",
          "description": "Major brands are using the U.S. Open tennis tournament to show off how they're embracing tech like augmented reality, NFTs, and VR.",
          "link": "https://decrypt.co/154542/tennis-meets-tech-tiffany-amex-wilson-us-open",
          "publishedOn": "2023-09-01T15:49:52.000Z",
          "wordCount": 10064,
          "title": "Tennis Meets Tech as Tiffany, Amex, Wilson Descend Upon US Open",
          "enclosure": {
            "url": "https://img.decrypt.co/insecure/rs:fill:1024:512:1:0/plain/https://cdn.decrypt.co/wp-content/uploads/2023/09/tiffany-usopen-lead-gID_7.png@png",
            "length": "1000000",
            "type": "image/png"
          },
          "imageUrl": "https://img.decrypt.co/insecure/rs:fill:1024:512:1:0/plain/https://cdn.decrypt.co/wp-content/uploads/2023/09/tiffany-usopen-lead-gID_7.png@png"
        },
        {
          "id": "https://decrypt.co/videos/interviews/qv3VwNmM/interview-how-will-aurory-use-nfts-and-crypto",
          "author": null,
          "description": "Michael Natoli, Aurory's Head of Marketing and Business Development, tells Decrypt's Jason Nelson about how the Aurory games will use NFTs and crypto and shares the studio's broader stance on the tech.",
          "link": "https://decrypt.co/videos/interviews/qv3VwNmM/interview-how-will-aurory-use-nfts-and-crypto",
          "publishedOn": "2023-09-01T15:27:00.000Z",
          "wordCount": 6578,
          "title": "INTERVIEW: How Will Aurory Use NFTs and Crypto?",
          "enclosure": {
            "url": "https://cdn.jwplayer.com/v2/media/qv3VwNmM/poster.jpg",
            "length": "1000000",
            "type": "image/png"
          },
          "imageUrl": "https://cdn.jwplayer.com/v2/media/qv3VwNmM/poster.jpg"
        },
        {
          "id": "https://decrypt.co/?p=154593",
          "author": "Andrew Throuvalas",
          "description": "Experts say there’s still room for improvement, but that Cambridge’s new model is a big step forward.",
          "link": "https://decrypt.co/154593/cambridge-updates-bitcoin-mining-index-reveal-true-power-consumption",
          "publishedOn": "2023-09-01T14:58:23.000Z",
          "wordCount": 9228,
          "title": "Cambridge Updates Bitcoin Mining Index to Reveal True Power Consumption",
          "enclosure": {
            "url": "https://img.decrypt.co/insecure/rs:fill:1024:512:1:0/plain/https://cdn.decrypt.co/wp-content/uploads/2023/02/bitcoin-mining-rig-1-gID_7.jpeg@png",
            "length": "1000000",
            "type": "image/png"
          },
          "imageUrl": "https://img.decrypt.co/insecure/rs:fill:1024:512:1:0/plain/https://cdn.decrypt.co/wp-content/uploads/2023/02/bitcoin-mining-rig-1-gID_7.jpeg@png"
        },
        {
          "id": "https://decrypt.co/videos/interviews/OeD4uoLj/google-clouds-james-tromans-on-the-intersection-of-ai-and-web3",
          "author": null,
          "description": "Google's Global Head of Google Cloud for Web3 James Tromans sat down with Decrypt's Jason Nelson to discuss how AI can help Web3 companies come to market faster and the real value of Web3 tools.",
          "link": "https://decrypt.co/videos/interviews/OeD4uoLj/google-clouds-james-tromans-on-the-intersection-of-ai-and-web3",
          "publishedOn": "2023-09-01T14:00:00.000Z",
          "wordCount": 6308,
          "title": "Google Cloud's James Tromans on the Intersection of AI and Web3",
          "enclosure": {
            "url": "https://cdn.jwplayer.com/v2/media/OeD4uoLj/poster.jpg",
            "length": "1000000",
            "type": "image/png"
          },
          "imageUrl": "https://cdn.jwplayer.com/v2/media/OeD4uoLj/poster.jpg"
        },
        {
          "id": "https://decrypt.co/?p=154580",
          "author": "Andrew Asmakov",
          "description": "One possible solution would be for Tether to reconsider its redemption fee and minimum redeemable amount, says a Kaiko analyst.",
          "link": "https://decrypt.co/154580/tethers-stablecoin-usdt-has-a-peg-stability-problem-claims-analyst",
          "publishedOn": "2023-09-01T12:15:36.000Z",
          "wordCount": 9446,
          "title": "Tether's Stablecoin USDT 'Has a Peg Stability Problem', Claims Analyst",
          "enclosure": {
            "url": "https://img.decrypt.co/insecure/rs:fill:1024:512:1:0/plain/https://cdn.decrypt.co/wp-content/uploads/2022/10/tether-stablecoin-gID_7.jpeg@png",
            "length": "1000000",
            "type": "image/png"
          },
          "imageUrl": "https://img.decrypt.co/insecure/rs:fill:1024:512:1:0/plain/https://cdn.decrypt.co/wp-content/uploads/2022/10/tether-stablecoin-gID_7.jpeg@png"
        },
        {
          "id": "https://decrypt.co/?p=154583",
          "author": "Nivesh Rustgi",
          "description": "Trading volumes for the largest cryptocurrencies in Bitcoin and Ethereum are on track for their worst quarter in four years.",
          "link": "https://decrypt.co/154583/bitcoin-ethereum-trading-volumes-headed-worst-quarter-since-2019",
          "publishedOn": "2023-09-01T12:05:45.000Z",
          "wordCount": 8906,
          "title": "Bitcoin, Ethereum Trading Volumes Headed for Worst Quarter Since 2019",
          "enclosure": {
            "url": "https://img.decrypt.co/insecure/rs:fill:1024:512:1:0/plain/https://cdn.decrypt.co/wp-content/uploads/2023/03/crypto-liquidity-gID_7.jpg@png",
            "length": "1000000",
            "type": "image/png"
          },
          "imageUrl": "https://img.decrypt.co/insecure/rs:fill:1024:512:1:0/plain/https://cdn.decrypt.co/wp-content/uploads/2023/03/crypto-liquidity-gID_7.jpg@png"
        },
        {
          "id": "https://decrypt.co/?p=153195",
          "author": "Nathan Reiff",
          "description": "It is difficult to properly assess cryptocurrencies through the lenses of traditional finance—it is even challenging to determine which agencies may be responsible for their oversight.",
          "link": "https://decrypt.co/resources/whos-who-in-global-crypto-regulation",
          "publishedOn": "2023-09-01T10:50:40.000Z",
          "wordCount": 12388,
          "title": "Who’s Who in Global Crypto Regulation",
          "enclosure": {
            "url": "https://img.decrypt.co/insecure/rs:fill:1024:512:1:0/plain/https://cdn.decrypt.co/wp-content/uploads/2023/03/5-defi-taxes-1-gID_7-pID_4.png@png",
            "length": "1000000",
            "type": "image/png"
          },
          "imageUrl": "https://img.decrypt.co/insecure/rs:fill:1024:512:1:0/plain/https://cdn.decrypt.co/wp-content/uploads/2023/03/5-defi-taxes-1-gID_7-pID_4.png@png"
        },
        {
          "id": "https://decrypt.co/?p=121725",
          "author": "Kade Garrett",
          "description": "Considered by some to be a currency without a state, the price of Bitcoin (BTC) has rapidly ascended and descended. What determines the current Bitcoin price?",
          "link": "https://decrypt.co/resources/what-determines-the-price-of-bitcoin-2",
          "publishedOn": "2023-09-01T10:38:54.000Z",
          "wordCount": 9168,
          "title": "What Determines the Price of Bitcoin?",
          "enclosure": {
            "url": "https://img.decrypt.co/insecure/rs:fill:1024:512:1:0/plain/https://cdn.decrypt.co/wp-content/uploads/2022/07/bitcoin-nodes-gID_1-pID_4.png@png",
            "length": "1000000",
            "type": "image/png"
          },
          "imageUrl": "https://img.decrypt.co/insecure/rs:fill:1024:512:1:0/plain/https://cdn.decrypt.co/wp-content/uploads/2022/07/bitcoin-nodes-gID_1-pID_4.png@png"
        },
        {
          "id": "https://decrypt.co/?p=154565",
          "author": "Nivesh Rustgi",
          "description": "Bitcoin puked gains from earlier this week after Grayscale's legal victory, as the SEC again punted on several spot Bitcoin ETF applications.",
          "link": "https://decrypt.co/154565/bitcoin-ethereum-drop-sec-delays-etf-decision",
          "publishedOn": "2023-09-01T09:31:09.000Z",
          "wordCount": 9142,
          "title": "Bitcoin, Ethereum Drop After SEC Delays ETF Decision",
          "enclosure": {
            "url": "https://img.decrypt.co/insecure/rs:fill:1024:512:1:0/plain/https://cdn.decrypt.co/wp-content/uploads/2022/01/shutterstock_1012491031-gID_7.jpg@png",
            "length": "1000000",
            "type": "image/png"
          },
          "imageUrl": "https://img.decrypt.co/insecure/rs:fill:1024:512:1:0/plain/https://cdn.decrypt.co/wp-content/uploads/2022/01/shutterstock_1012491031-gID_7.jpg@png"
        },
        {
          "id": "https://decrypt.co/?p=154526",
          "author": "Kate Irwin",
          "description": "The Bored Ape Yacht Club creator's Otherside: Legends of the Mara game experience is about to open up, letting players evolve egg-like NFTs.",
          "link": "https://decrypt.co/154526/otherside-legends-mara-open-beta-launching-september",
          "publishedOn": "2023-09-01T00:03:33.000Z",
          "wordCount": 9359,
          "title": "Otherside: Legends of the Mara Open Beta Launching in September",
          "enclosure": {
            "url": "https://img.decrypt.co/insecure/rs:fill:1024:512:1:0/plain/https://cdn.decrypt.co/wp-content/uploads/2023/08/LOTM-22222-Cropped-gID_7.jpg@png",
            "length": "1000000",
            "type": "image/png"
          },
          "imageUrl": "https://img.decrypt.co/insecure/rs:fill:1024:512:1:0/plain/https://cdn.decrypt.co/wp-content/uploads/2023/08/LOTM-22222-Cropped-gID_7.jpg@png"
        },
        {
          "id": "https://decrypt.co/?p=154522",
          "author": "Kate Irwin",
          "description": "The Brazilian YouTuber went on an emotional rollercoaster this week—but there's a mostly happy ending to his tale.",
          "link": "https://decrypt.co/154522/youtuber-loses-60k-worth-crypto-after-showing-seed-phrase-stream",
          "publishedOn": "2023-08-31T23:42:16.000Z",
          "wordCount": 9476,
          "title": "YouTuber Loses $60K Worth of Crypto After Showing Seed Phrases on Stream",
          "enclosure": {
            "url": "https://img.decrypt.co/insecure/rs:fill:1024:512:1:0/plain/https://cdn.decrypt.co/wp-content/uploads/2023/08/sad-gamer-shutterstock-gID_7.png@png",
            "length": "1000000",
            "type": "image/png"
          },
          "imageUrl": "https://img.decrypt.co/insecure/rs:fill:1024:512:1:0/plain/https://cdn.decrypt.co/wp-content/uploads/2023/08/sad-gamer-shutterstock-gID_7.png@png"
        },
        {
          "id": "https://decrypt.co/?p=154504",
          "author": "Sander Lutz",
          "description": "By casting the SEC as a villainous deep state entity situated above politics, presidential candidate Vivek Ramaswamy is reshaping the calculus on what has often been a partisan issue.",
          "link": "https://decrypt.co/154504/vivek-ramaswamy-changing-presidential-campaign-discourse-crypto",
          "publishedOn": "2023-08-31T22:23:51.000Z",
          "wordCount": 9558,
          "title": "Vivek Ramaswamy Is Changing Presidential Campaign Discourse on Crypto",
          "enclosure": {
            "url": "https://img.decrypt.co/insecure/rs:fill:1024:512:1:0/plain/https://cdn.decrypt.co/wp-content/uploads/2023/08/vivek-shutterstock-gID_7.png@png",
            "length": "1000000",
            "type": "image/png"
          },
          "imageUrl": "https://img.decrypt.co/insecure/rs:fill:1024:512:1:0/plain/https://cdn.decrypt.co/wp-content/uploads/2023/08/vivek-shutterstock-gID_7.png@png"
        },
        {
          "id": "https://decrypt.co/?p=154510",
          "author": "Jason Nelson",
          "description": "Hiber3D has integrated Google's AI tools to give creators the ability to type what they want to see—and generate an immersive world.",
          "link": "https://decrypt.co/154510/google-generative-ai-tools-turn-text-online-worlds",
          "publishedOn": "2023-08-31T20:54:58.000Z",
          "wordCount": 9271,
          "title": "Google's Generative AI Tools Now Turn Text Into Online Worlds",
          "enclosure": {
            "url": "https://img.decrypt.co/insecure/rs:fill:1024:512:1:0/plain/https://cdn.decrypt.co/wp-content/uploads/2023/08/hiberworld-screen-gID_7.jpeg@png",
            "length": "1000000",
            "type": "image/png"
          },
          "imageUrl": "https://img.decrypt.co/insecure/rs:fill:1024:512:1:0/plain/https://cdn.decrypt.co/wp-content/uploads/2023/08/hiberworld-screen-gID_7.jpeg@png"
        },
        {
          "id": "https://decrypt.co/?p=154499",
          "author": "Alyssa Hertig",
          "description": "Researchers found a way to use a local \"mesh network\" to connect nodes via Bluetooth and WiFi, building a local Lightning Network they call LNMesh.",
          "link": "https://decrypt.co/154499/no-internet-you-could-still-use-bitcoin-on-the-lightning-network",
          "publishedOn": "2023-08-31T20:05:29.000Z",
          "wordCount": 10224,
          "title": "No Internet? You Could Still Use Bitcoin on the Lightning Network",
          "enclosure": {
            "url": "https://img.decrypt.co/insecure/rs:fill:1024:512:1:0/plain/https://cdn.decrypt.co/wp-content/uploads/2023/08/you-are-offline-bitcoin-btc-gID_7.jpg@png",
            "length": "1000000",
            "type": "image/png"
          },
          "imageUrl": "https://img.decrypt.co/insecure/rs:fill:1024:512:1:0/plain/https://cdn.decrypt.co/wp-content/uploads/2023/08/you-are-offline-bitcoin-btc-gID_7.jpg@png"
        },
        {
          "id": "https://decrypt.co/?p=154505",
          "author": "Stacy Elliott,André Beganski",
          "description": "Wisdom Tree, Fidelity, and BlackRock Bitcoin ETF applications have all been delayed until October at the earliest.",
          "link": "https://decrypt.co/154505/sec-bitcoin-etfs-more-delays",
          "publishedOn": "2023-08-31T19:50:43.000Z",
          "wordCount": 9381,
          "title": "SEC Punts on Bitcoin ETFs, Including BlackRock, Fidelity and More",
          "enclosure": {
            "url": "https://img.decrypt.co/insecure/rs:fill:1024:512:1:0/plain/https://cdn.decrypt.co/wp-content/uploads/2023/02/sec-crypto-regulations-gID_1.jpg@png",
            "length": "1000000",
            "type": "image/png"
          },
          "imageUrl": "https://img.decrypt.co/insecure/rs:fill:1024:512:1:0/plain/https://cdn.decrypt.co/wp-content/uploads/2023/02/sec-crypto-regulations-gID_1.jpg@png"
        },
        {
          "id": "https://decrypt.co/?p=154494",
          "author": "André Beganski",
          "description": "GBTC’s shrinking discount relative to its Bitcoin holdings was nearly 50% last December. Traders who bought the dip are sitting on big gains.",
          "link": "https://decrypt.co/154494/grayscale-bitcoin-trust-investors-who-bought-december-dip-are-up-137",
          "publishedOn": "2023-08-31T19:24:07.000Z",
          "wordCount": 9184,
          "title": "Grayscale Bitcoin Trust Investors Who Bought December Dip Are Up 137%",
          "enclosure": {
            "url": "https://img.decrypt.co/insecure/rs:fill:1024:512:1:0/plain/https://cdn.decrypt.co/wp-content/uploads/2022/12/grayscale-bitcoin-trust-gID_7.jpg@png",
            "length": "1000000",
            "type": "image/png"
          },
          "imageUrl": "https://img.decrypt.co/insecure/rs:fill:1024:512:1:0/plain/https://cdn.decrypt.co/wp-content/uploads/2022/12/grayscale-bitcoin-trust-gID_7.jpg@png"
        },
        {
          "id": "https://decrypt.co/?p=154469",
          "author": "Stephanie Hirschmiller",
          "description": "Sportswear and lifestyle giant Adidas is partnering with artists on NFT drops and other products, kicking off during Korea Blockchain Week.",
          "link": "https://decrypt.co/154469/adidas-creates-residency-nft-artists-plans-physical-collabs",
          "publishedOn": "2023-08-31T18:29:34.000Z",
          "wordCount": 9151,
          "title": "Adidas Creates Residency for NFT Artists With Plans for Physical Collabs",
          "enclosure": {
            "url": "https://img.decrypt.co/insecure/rs:fill:1024:512:1:0/plain/https://cdn.decrypt.co/wp-content/uploads/2023/08/DearNostalgia_LE-scaled-gID_7.jpeg@png",
            "length": "1000000",
            "type": "image/png"
          },
          "imageUrl": "https://img.decrypt.co/insecure/rs:fill:1024:512:1:0/plain/https://cdn.decrypt.co/wp-content/uploads/2023/08/DearNostalgia_LE-scaled-gID_7.jpeg@png"
        },
        {
          "id": "https://decrypt.co/?p=154450",
          "author": "Liam J. Kelly",
          "description": "With infrastructure and UX solved, Argent and the Starknet Foundation are teaming up again to fund builders looking to launch on Starknet.",
          "link": "https://decrypt.co/154450/argent-starknet-foundation-tag-several-millions-new-startup-studio",
          "publishedOn": "2023-08-31T17:01:02.000Z",
          "wordCount": 8645,
          "title": "Argent, Starknet Foundation Tag 'Several Millions' for New Startup Studio",
          "enclosure": {
            "url": "https://img.decrypt.co/insecure/rs:fill:1024:512:1:0/plain/https://cdn.decrypt.co/wp-content/uploads/2023/08/starknet-foundation-argent-gID_7.jpg@png",
            "length": "1000000",
            "type": "image/png"
          },
          "imageUrl": "https://img.decrypt.co/insecure/rs:fill:1024:512:1:0/plain/https://cdn.decrypt.co/wp-content/uploads/2023/08/starknet-foundation-argent-gID_7.jpg@png"
        },
        {
          "id": "https://decrypt.co/?p=154449",
          "author": "Andrew Hayward",
          "description": "How much Bitcoin can you really earn from these iOS and Android games? After a few hours of Bitcoin Pop and Bitcoin Bay: Not much.",
          "link": "https://decrypt.co/154449/earn-bitcoin-playing-mobile-bubble-shooters-heres-how-much",
          "publishedOn": "2023-08-31T16:58:47.000Z",
          "wordCount": 10508,
          "title": "You Can Earn Bitcoin by Playing Mobile Bubble Shooters—Here's How Much",
          "enclosure": {
            "url": "https://img.decrypt.co/insecure/rs:fill:1024:512:1:0/plain/https://cdn.decrypt.co/wp-content/uploads/2023/08/bitcoin-bay-art-gID_7.png@png",
            "length": "1000000",
            "type": "image/png"
          },
          "imageUrl": "https://img.decrypt.co/insecure/rs:fill:1024:512:1:0/plain/https://cdn.decrypt.co/wp-content/uploads/2023/08/bitcoin-bay-art-gID_7.png@png"
        },
        {
          "id": "https://decrypt.co/?p=150832",
          "author": "Nathan Reiff",
          "description": "Worldcoin has introduced a concept called “proof of personhood\" to keep AI bots out of its global financial network.",
          "link": "https://decrypt.co/resources/what-is-worldcoin-the-app-and-token-that-protects-your-personhood",
          "publishedOn": "2023-08-31T13:44:29.000Z",
          "wordCount": 12325,
          "title": "What is Worldcoin? Sam Altman's Eye-Scanning Global ID 'Orb' Project Hits Regulatory Roadblocks",
          "enclosure": {
            "url": "https://img.decrypt.co/insecure/rs:fill:1024:512:1:0/plain/https://cdn.decrypt.co/wp-content/uploads/2023/07/4-gID_5-pID_5.png@png",
            "length": "1000000",
            "type": "image/png"
          },
          "imageUrl": "https://img.decrypt.co/insecure/rs:fill:1024:512:1:0/plain/https://cdn.decrypt.co/wp-content/uploads/2023/07/4-gID_5-pID_5.png@png"
        },
        {
          "id": "https://decrypt.co/?p=154426",
          "author": "Nivesh Rustgi",
          "description": "PancakeSwap joins DeFi heavyweights like Uniswap, SushiSwap, and 1inch launching on the buzzy layer-2 network Base.",
          "link": "https://decrypt.co/154426/pancakeswap-expands-coinbase-incubated-base-network",
          "publishedOn": "2023-08-31T13:01:10.000Z",
          "wordCount": 8294,
          "title": "PancakeSwap Expands to Coinbase-Incubated Base Network",
          "enclosure": {
            "url": "https://img.decrypt.co/insecure/rs:fill:1024:512:1:0/plain/https://cdn.decrypt.co/wp-content/uploads/2023/04/pancakeswap-cake-token-gID_7.jpg@png",
            "length": "1000000",
            "type": "image/png"
          },
          "imageUrl": "https://img.decrypt.co/insecure/rs:fill:1024:512:1:0/plain/https://cdn.decrypt.co/wp-content/uploads/2023/04/pancakeswap-cake-token-gID_7.jpg@png"
        },
        {
          "id": "https://decrypt.co/?p=154428",
          "author": "Andrew Asmakov",
          "description": "Nexo's new functionality is now available to Europeans, enabling users to instantly toggle between debit and credit modes.",
          "link": "https://decrypt.co/154428/nexo-rolls-out-dual-mode-flagship-crypto-card",
          "publishedOn": "2023-08-31T13:01:02.000Z",
          "wordCount": 8795,
          "title": "Nexo Rolls Out 'Dual Mode' for its Flagship Crypto Card",
          "enclosure": {
            "url": "https://img.decrypt.co/insecure/rs:fill:1024:512:1:0/plain/https://cdn.decrypt.co/wp-content/uploads/2023/08/Nexo-Card-gID_7.jpeg@png",
            "length": "1000000",
            "type": "image/png"
          },
          "imageUrl": "https://img.decrypt.co/insecure/rs:fill:1024:512:1:0/plain/https://cdn.decrypt.co/wp-content/uploads/2023/08/Nexo-Card-gID_7.jpeg@png"
        },
        {
          "id": "https://decrypt.co/?p=154434",
          "author": "Nivesh Rustgi",
          "description": "Swift, Chainlink, and 10 banks teamed up to test the ability to move financial assets across traditional rails and blockchain networks.",
          "link": "https://decrypt.co/154434/chainlink-swift-complete-tokenization-tests-with-citi-bank-bny-mellon-others",
          "publishedOn": "2023-08-31T12:19:51.000Z",
          "wordCount": 8416,
          "title": "Chainlink, Swift Complete Tokenization Tests With Citi Bank, BNY Mellon, and Others",
          "enclosure": {
            "url": "https://img.decrypt.co/insecure/rs:fill:1024:512:1:0/plain/https://cdn.decrypt.co/wp-content/uploads/2023/08/swift-interoperability-crypto-gID_7.jpg@png",
            "length": "1000000",
            "type": "image/png"
          },
          "imageUrl": "https://img.decrypt.co/insecure/rs:fill:1024:512:1:0/plain/https://cdn.decrypt.co/wp-content/uploads/2023/08/swift-interoperability-crypto-gID_7.jpg@png"
        },
        {
          "id": "https://decrypt.co/?p=154427",
          "author": "Pedro Solimano",
          "description": "The crypto exchange will gradually end support for its native stablecoin, after Paxos halted the minting of new BUSD.",
          "link": "https://decrypt.co/154427/binance-to-phase-out-busd-support-encourages-users-to-convert-into-other-stablecoins",
          "publishedOn": "2023-08-31T12:06:37.000Z",
          "wordCount": 8642,
          "title": "Binance to Phase Out BUSD Support, ‘Encourages’ Users To Convert Into Other Stablecoins",
          "enclosure": {
            "url": "https://img.decrypt.co/insecure/rs:fill:1024:512:1:0/plain/https://cdn.decrypt.co/wp-content/uploads/2023/02/busd-binance-usd-stablecoin-gID_7.jpeg@png",
            "length": "1000000",
            "type": "image/png"
          },
          "imageUrl": "https://img.decrypt.co/insecure/rs:fill:1024:512:1:0/plain/https://cdn.decrypt.co/wp-content/uploads/2023/02/busd-binance-usd-stablecoin-gID_7.jpeg@png"
        },
        {
          "id": "https://decrypt.co/?p=154425",
          "author": "Mattis Meichler",
          "description": "The defense for the disgraced crypto founder Sam Bankman-Fried has until September 7 to appeal for a trial postponement.",
          "link": "https://decrypt.co/154425/judge-mulls-delaying-bankman-fried-court-date-amidst-defense-pleas",
          "publishedOn": "2023-08-31T11:17:19.000Z",
          "wordCount": 8958,
          "title": "Judge Mulls Delaying Bankman-Fried's Court Date Amidst Defense Pleas",
          "enclosure": {
            "url": "https://img.decrypt.co/insecure/rs:fill:1024:512:1:0/plain/https://cdn.decrypt.co/wp-content/uploads/2023/01/sam-bankman-fried-ftx-gID_7.jpeg@png",
            "length": "1000000",
            "type": "image/png"
          },
          "imageUrl": "https://img.decrypt.co/insecure/rs:fill:1024:512:1:0/plain/https://cdn.decrypt.co/wp-content/uploads/2023/01/sam-bankman-fried-ftx-gID_7.jpeg@png"
        },
        {
          "id": "https://decrypt.co/?p=154421",
          "author": "Nivesh Rustgi",
          "description": "DeFi deposits on the Base network hit a new all-time high thanks to liquidity mining incentives from the decentralized exchange Aerodrome.",
          "link": "https://decrypt.co/154421/base-defi-deposits-soar-yield-farmers-plant-aerodrome-harvest",
          "publishedOn": "2023-08-31T10:50:17.000Z",
          "wordCount": 8604,
          "title": "DeFi Deposits on Base Soar as Yield Farmers Plant Aerodrome Harvest",
          "enclosure": {
            "url": "https://img.decrypt.co/insecure/rs:fill:1024:512:1:0/plain/https://cdn.decrypt.co/wp-content/uploads/2023/07/Base-16x9-1-gID_7.jpg@png",
            "length": "1000000",
            "type": "image/png"
          },
          "imageUrl": "https://img.decrypt.co/insecure/rs:fill:1024:512:1:0/plain/https://cdn.decrypt.co/wp-content/uploads/2023/07/Base-16x9-1-gID_7.jpg@png"
        },
        {
          "id": "https://decrypt.co/?p=55615",
          "author": "Matt Hussey",
          "description": "In this guide we explain how staking and lending works in cryptocurrencies, their benefits, but also their potential downsides.",
          "link": "https://decrypt.co/resources/how-to-invest-in-cryptocurrencies-staking-and-lending",
          "publishedOn": "2023-08-31T09:13:07.000Z",
          "wordCount": 10490,
          "title": "What are Staking and Lending? The Crypto Investment That Can Earn Interest",
          "enclosure": {
            "url": "https://img.decrypt.co/insecure/rs:fill:1024:512:1:0/plain/https://cdn.decrypt.co/wp-content/uploads/2021/01/StakingCoins-gID_7-pID_2.png@png",
            "length": "1000000",
            "type": "image/png"
          },
          "imageUrl": "https://img.decrypt.co/insecure/rs:fill:1024:512:1:0/plain/https://cdn.decrypt.co/wp-content/uploads/2021/01/StakingCoins-gID_7-pID_2.png@png"
        },
        {
          "id": "https://decrypt.co/?p=154418",
          "author": "Andrew Asmakov",
          "description": "Robinhood's self-custodial crypto wallet now lets users dive deep into the world of decentralized finance via Ethereum swaps.",
          "link": "https://decrypt.co/154418/robinhood-wallet-expands-crypto-offering-add-bitcoin-dogecoin-ethereum-swaps",
          "publishedOn": "2023-08-31T09:08:19.000Z",
          "wordCount": 9059,
          "title": "Robinhood Wallet Expands Crypto Offering to Add Bitcoin, Dogecoin, and Ethereum Swaps",
          "enclosure": {
            "url": "https://img.decrypt.co/insecure/rs:fill:1024:512:1:0/plain/https://cdn.decrypt.co/wp-content/uploads/2021/01/Robinhood-gID_7.jpg@png",
            "length": "1000000",
            "type": "image/png"
          },
          "imageUrl": "https://img.decrypt.co/insecure/rs:fill:1024:512:1:0/plain/https://cdn.decrypt.co/wp-content/uploads/2021/01/Robinhood-gID_7.jpg@png"
        },
        {
          "id": "https://decrypt.co/videos/explainers/HQGt1Vrq/mastering-nft-trading-degen-u",
          "author": null,
          "description": "Take Degen U's new course, Mastering NFT Trading, and earn an on-chain certificate. A top instructor will help you identify trends, seize the right moment to trade, weed out scams—and have fun while doing it!",
          "link": "https://decrypt.co/videos/explainers/HQGt1Vrq/mastering-nft-trading-degen-u",
          "publishedOn": "2023-08-29T07:08:35.000Z",
          "wordCount": 6276,
          "title": "Mastering NFT Trading - Degen U",
          "enclosure": {
            "url": "https://cdn.jwplayer.com/v2/media/HQGt1Vrq/poster.jpg",
            "length": "1000000",
            "type": "image/png"
          },
          "imageUrl": "https://cdn.jwplayer.com/v2/media/HQGt1Vrq/poster.jpg"
        },
        {
          "id": "https://decrypt.co/videos/interviews/LpznLhtx/space-nation-ceo-on-working-with-independence-day-director-roland-emmerich",
          "author": null,
          "description": "Jerome Wu, CEO of Space Nation, tells Decrypt's Kate Irwin about the upcoming Space Nation Online game in development and shares details on Space Nation Cofounder Roland Emmerich's role in the project.",
          "link": "https://decrypt.co/videos/interviews/LpznLhtx/space-nation-ceo-on-working-with-independence-day-director-roland-emmerich",
          "publishedOn": "2023-08-28T17:34:00.000Z",
          "wordCount": 6293,
          "title": "Space Nation CEO on Working With 'Independence Day' Director Roland Emmerich",
          "enclosure": {
            "url": "https://cdn.jwplayer.com/v2/media/LpznLhtx/poster.jpg",
            "length": "1000000",
            "type": "image/png"
          },
          "imageUrl": "https://cdn.jwplayer.com/v2/media/LpznLhtx/poster.jpg"
        },
        {
          "id": "https://decrypt.co/videos/interviews/qUE1RlDx/game-review-champions-arena-from-gala-games",
          "author": null,
          "description": "Champions Arena is a turn-based fantasy RPG from Gala Games, where characters can become NFTs and crypto can be used to purchase gems, one of the game's synthetic currencies. Decrypt's Kate Irwin takes us inside the game for her thoughts on the fun, mobile-first title.",
          "link": "https://decrypt.co/videos/interviews/qUE1RlDx/game-review-champions-arena-from-gala-games",
          "publishedOn": "2023-08-25T23:00:00.000Z",
          "wordCount": 6334,
          "title": "GAME REVIEW: Champions Arena from Gala Games",
          "enclosure": {
            "url": "https://cdn.jwplayer.com/v2/media/qUE1RlDx/poster.jpg",
            "length": "1000000",
            "type": "image/png"
          },
          "imageUrl": "https://cdn.jwplayer.com/v2/media/qUE1RlDx/poster.jpg"
        },
        {
          "id": "https://decrypt.co/videos/interviews/X3RKdsaG/apex-legends-voice-actor-ben-prendergast-on-the-future-of-gaming",
          "author": null,
          "description": "Voice actor Ben Prendergast, who's voiced characters in games like Apex Legends and God of War Ragnarok, shares his opinions on the tech space's history of \"bubbles\" and whether blockchain gaming has a future.",
          "link": "https://decrypt.co/videos/interviews/X3RKdsaG/apex-legends-voice-actor-ben-prendergast-on-the-future-of-gaming",
          "publishedOn": "2023-08-24T18:15:00.000Z",
          "wordCount": 6303,
          "title": "Apex Legends Voice Actor Ben Prendergast on the Future of Gaming",
          "enclosure": {
            "url": "https://cdn.jwplayer.com/v2/media/X3RKdsaG/poster.jpg",
            "length": "1000000",
            "type": "image/png"
          },
          "imageUrl": "https://cdn.jwplayer.com/v2/media/X3RKdsaG/poster.jpg"
        },
        {
          "id": "https://decrypt.co/videos/interviews/yVQaZI71/the-future-of-ai-stardom-and-robotics-with-singularitynet-coo-janet-adams-and-desdemona",
          "author": null,
          "description": "In this interview, SingularityNET COO Janet Adams explains the intricate details that went into creating the Desdemona robot AI from Hanson Robotics and future plans for the AI Diva.",
          "link": "https://decrypt.co/videos/interviews/yVQaZI71/the-future-of-ai-stardom-and-robotics-with-singularitynet-coo-janet-adams-and-desdemona",
          "publishedOn": "2023-08-23T16:45:46.000Z",
          "wordCount": 6263,
          "title": "The future of AI Stardom and Robotics with SingularityNET COO Janet Adams and Desdemona",
          "enclosure": {
            "url": "https://cdn.jwplayer.com/v2/media/yVQaZI71/poster.jpg",
            "length": "1000000",
            "type": "image/png"
          },
          "imageUrl": "https://cdn.jwplayer.com/v2/media/yVQaZI71/poster.jpg"
        },
        {
          "id": "https://decrypt.co/videos/interviews/rdynom8C/crypto-a-no-brainer-for-video-games-says-mino-games-ceo",
          "author": null,
          "description": "Mino Games CEO Sasha MacKinnon, developer of the upcoming Dimensionals game, tells Decrypt's Kate Irwin about the studio's approach to digital collectibles.",
          "link": "https://decrypt.co/videos/interviews/rdynom8C/crypto-a-no-brainer-for-video-games-says-mino-games-ceo",
          "publishedOn": "2023-08-22T18:41:00.000Z",
          "wordCount": 6204,
          "title": "Crypto a 'No-Brainer' for Video Games, Says Mino Games CEO",
          "enclosure": {
            "url": "https://cdn.jwplayer.com/v2/media/rdynom8C/poster.jpg",
            "length": "1000000",
            "type": "image/png"
          },
          "imageUrl": "https://cdn.jwplayer.com/v2/media/rdynom8C/poster.jpg"
        },
        {
          "id": "https://decrypt.co/videos/interviews/tc2nKeqA/michael-wagners-controversial-take-on-crypto-in-games",
          "author": null,
          "description": "At Solana's PlayGG, Star Atlas CEO Michael Wagner shares his \"controversial take\" on crypto in games, shares the challenges of developing the upcoming scifi game, and how crypto's volatility has changed his perspective with Decrypt's Jason Nelson.",
          "link": "https://decrypt.co/videos/interviews/tc2nKeqA/michael-wagners-controversial-take-on-crypto-in-games",
          "publishedOn": "2023-08-21T16:51:00.000Z",
          "wordCount": 6300,
          "title": "Michael Wagner's 'Controversial Take' on Crypto in Games",
          "enclosure": {
            "url": "https://cdn.jwplayer.com/v2/media/tc2nKeqA/poster.jpg",
            "length": "1000000",
            "type": "image/png"
          },
          "imageUrl": "https://cdn.jwplayer.com/v2/media/tc2nKeqA/poster.jpg"
        },
        {
          "id": "https://decrypt.co/videos/interviews/uCzW3K7P/interview-angelic-ceo-on-building-the-sci-fi-rpg-on-solana-and-ethereum",
          "author": null,
          "description": "Angelic is a sci-fi roleplay game in development that will be free-to-play and offer optional, opt-in crypto features on Solana and Ethereum and a governance token. Metaverse Game Studios CEO and Founder Erkan Bayol tells Decrypt's Jason Nelson about how he sees AAA traditional games as Angelic's main competitors and shares his vision for the game.",
          "link": "https://decrypt.co/videos/interviews/uCzW3K7P/interview-angelic-ceo-on-building-the-sci-fi-rpg-on-solana-and-ethereum",
          "publishedOn": "2023-08-18T15:58:00.000Z",
          "wordCount": 6419,
          "title": "Interview: Angelic CEO on Building the Sci-Fi RPG on Solana and Ethereum",
          "enclosure": {
            "url": "https://cdn.jwplayer.com/v2/media/uCzW3K7P/poster.jpg",
            "length": "1000000",
            "type": "image/png"
          },
          "imageUrl": "https://cdn.jwplayer.com/v2/media/uCzW3K7P/poster.jpg"
        },
        {
          "id": "https://decrypt.co/videos/interviews/IOIrmb0N/apex-legends-voice-actor-on-ais-impact-on-video-games",
          "author": null,
          "description": "Ben Prendergast is an actor who has voiced characters like Apex Legends' Fuse, God of War Ragnarok's Tyr, and Patroclus in Hades. But as debates swirl around the use of artificial intelligence in entertainment in light of the SAG-AFTRA and WGA strikes, Prendergast gives Decrypt's Kate Irwin his honest take on the potential use of AI actors in games.",
          "link": "https://decrypt.co/videos/interviews/IOIrmb0N/apex-legends-voice-actor-on-ais-impact-on-video-games",
          "publishedOn": "2023-08-16T17:28:14.000Z",
          "wordCount": 6422,
          "title": "Apex Legends Voice Actor on AI's Impact on Video Games",
          "enclosure": {
            "url": "https://cdn.jwplayer.com/v2/media/IOIrmb0N/poster.jpg",
            "length": "1000000",
            "type": "image/png"
          },
          "imageUrl": "https://cdn.jwplayer.com/v2/media/IOIrmb0N/poster.jpg"
        },
        {
          "id": "https://decrypt.co/videos/interviews/WQCaahmH/star-atlas-ceo-on-developing-an-mmo-game",
          "author": null,
          "description": "Decrypt's Jason Nelson speaks with Star Atlas Founder and CEO Michael Wagner about the MMO game's approach to development, marketing, and blockchain integrations.",
          "link": "https://decrypt.co/videos/interviews/WQCaahmH/star-atlas-ceo-on-developing-an-mmo-game",
          "publishedOn": "2023-08-15T13:57:00.000Z",
          "wordCount": 6230,
          "title": "Star Atlas CEO on Developing an MMO Game",
          "enclosure": {
            "url": "https://cdn.jwplayer.com/v2/media/WQCaahmH/poster.jpg",
            "length": "1000000",
            "type": "image/png"
          },
          "imageUrl": "https://cdn.jwplayer.com/v2/media/WQCaahmH/poster.jpg"
        },
        {
          "id": "https://decrypt.co/videos/interviews/O0S201TB/aurorys-origin-story-how-jrpgs-inspired-the-games",
          "author": null,
          "description": "Decrypt's Jason Nelson talks to Aurory's Head of Marketing and Business Development Michael Natoli about the origins of the Aurory crypto games at the Solana PlayGG event.",
          "link": "https://decrypt.co/videos/interviews/O0S201TB/aurorys-origin-story-how-jrpgs-inspired-the-games",
          "publishedOn": "2023-08-14T16:57:00.000Z",
          "wordCount": 6250,
          "title": "Aurory's Origin Story: How JRPGs Inspired the Games",
          "enclosure": {
            "url": "https://cdn.jwplayer.com/v2/media/O0S201TB/poster.jpg",
            "length": "1000000",
            "type": "image/png"
          },
          "imageUrl": "https://cdn.jwplayer.com/v2/media/O0S201TB/poster.jpg"
        },
        {
          "id": "https://decrypt.co/videos/explainers/q8YVWJh4/parallel-tcg-inside-the-sci-fi-card-games-closed-beta",
          "author": null,
          "description": "Decrypt's Kate Irwin goes hands-on with Parallel’s closed beta on Windows PC to find out what sets it apart from other crypto card-battlers.",
          "link": "https://decrypt.co/videos/explainers/q8YVWJh4/parallel-tcg-inside-the-sci-fi-card-games-closed-beta",
          "publishedOn": "2023-08-11T15:27:00.000Z",
          "wordCount": 6234,
          "title": "Parallel TCG: Inside the Sci-Fi Card Game’s Closed Beta",
          "enclosure": {
            "url": "https://cdn.jwplayer.com/v2/media/q8YVWJh4/poster.jpg",
            "length": "1000000",
            "type": "image/png"
          },
          "imageUrl": "https://cdn.jwplayer.com/v2/media/q8YVWJh4/poster.jpg"
        },
        {
          "id": "https://decrypt.co/videos/interviews/Ud9wTd4s/web3-games-need-to-compete-with-all-games-says-solana-foundation-gm",
          "author": null,
          "description": "Solana Foundation's General Manager of Games Johnny Lee tells Decrypt's Jason Nelson about Solana's PlayGG conference and shares his take on crypto gaming and the \"play-to-earn\" concept.",
          "link": "https://decrypt.co/videos/interviews/Ud9wTd4s/web3-games-need-to-compete-with-all-games-says-solana-foundation-gm",
          "publishedOn": "2023-08-09T19:55:00.000Z",
          "wordCount": 6274,
          "title": "Web3 Games Need to Compete with All Games, Says Solana Foundation GM",
          "enclosure": {
            "url": "https://cdn.jwplayer.com/v2/media/Ud9wTd4s/poster.jpg",
            "length": "1000000",
            "type": "image/png"
          },
          "imageUrl": "https://cdn.jwplayer.com/v2/media/Ud9wTd4s/poster.jpg"
        },
        {
          "id": "https://decrypt.co/videos/interviews/BA4yE45A/many-early-blockchain-games-were-cash-grabs-says-twitch-streamer-alliestrasza",
          "author": null,
          "description": "\"I wrote them off,\" Twitch streamer Alliestrasza said of her initial thoughts on many early blockchain games. She tells Decrypt's Jason Nelson about how her perspective on Web3 games has evolved over time and now sees blockchain games getting significantly better.",
          "link": "https://decrypt.co/videos/interviews/BA4yE45A/many-early-blockchain-games-were-cash-grabs-says-twitch-streamer-alliestrasza",
          "publishedOn": "2023-08-07T16:38:00.000Z",
          "wordCount": 6338,
          "title": "Many Early Blockchain Games Were 'Cash Grabs,' Says Twitch Streamer Alliestrasza",
          "enclosure": {
            "url": "https://cdn.jwplayer.com/v2/media/BA4yE45A/poster.jpg",
            "length": "1000000",
            "type": "image/png"
          },
          "imageUrl": "https://cdn.jwplayer.com/v2/media/BA4yE45A/poster.jpg"
        },
        {
          "id": "https://decrypt.co/videos/live-events/tjK6i7lv/metalcore-game-preview-hands-on-with-the-titanfall-meets-destiny-nft-mashup",
          "author": null,
          "description": "MetalCore is an upcoming mech shooter developed by Studio 369, and it's being developed on Ethereum scaling network Immutable zkEVM. Decrypt contributor Ryan Gladwin played through the prologue and tested out the recent Alpha 3 online experience to get a sense of the NFT-infused mashup of Titanfall and Destiny.",
          "link": "https://decrypt.co/videos/live-events/tjK6i7lv/metalcore-game-preview-hands-on-with-the-titanfall-meets-destiny-nft-mashup",
          "publishedOn": "2023-08-04T19:46:06.000Z",
          "wordCount": 6380,
          "title": "'MetalCore' Game Preview: Hands-on With the 'Titanfall' Meets 'Destiny' NFT Mashup",
          "enclosure": {
            "url": "https://cdn.jwplayer.com/v2/media/tjK6i7lv/poster.jpg",
            "length": "1000000",
            "type": "image/png"
          },
          "imageUrl": "https://cdn.jwplayer.com/v2/media/tjK6i7lv/poster.jpg"
        }
      ]
    }
  ],
  "cliVersion": "1.15.1"
}